package com.xiaomi.push;

import java.util.ArrayList;

class dd
  extends cx
{
  cx jdField_a_of_type_ComXiaomiPushCx = this.jdField_b_of_type_ComXiaomiPushCx;
  
  /* Error */
  dd(db paramdb, String paramString, cx paramcx)
  {
    // Byte code:
    //   0: aload_0
    //   1: aload_1
    //   2: putfield 12	com/xiaomi/push/dd:jdField_a_of_type_ComXiaomiPushDb	Lcom/xiaomi/push/db;
    //   5: aload_0
    //   6: aload_3
    //   7: putfield 14	com/xiaomi/push/dd:jdField_b_of_type_ComXiaomiPushCx	Lcom/xiaomi/push/cx;
    //   10: aload_0
    //   11: aload_2
    //   12: invokespecial 17	com/xiaomi/push/cx:<init>	(Ljava/lang/String;)V
    //   15: aload_0
    //   16: aload_0
    //   17: getfield 14	com/xiaomi/push/dd:jdField_b_of_type_ComXiaomiPushCx	Lcom/xiaomi/push/cx;
    //   20: putfield 19	com/xiaomi/push/dd:jdField_a_of_type_ComXiaomiPushCx	Lcom/xiaomi/push/cx;
    //   23: aload_0
    //   24: aload_0
    //   25: getfield 22	com/xiaomi/push/dd:jdField_b_of_type_JavaLangString	Ljava/lang/String;
    //   28: putfield 22	com/xiaomi/push/dd:jdField_b_of_type_JavaLangString	Ljava/lang/String;
    //   31: aload_0
    //   32: getfield 14	com/xiaomi/push/dd:jdField_b_of_type_ComXiaomiPushCx	Lcom/xiaomi/push/cx;
    //   35: astore_1
    //   36: aload_1
    //   37: ifnull +11 -> 48
    //   40: aload_0
    //   41: aload_1
    //   42: getfield 25	com/xiaomi/push/cx:f	Ljava/lang/String;
    //   45: putfield 26	com/xiaomi/push/dd:f	Ljava/lang/String;
    //   48: return
    // Local variable table:
    //   start	length	slot	name	signature
    //   0	49	0	this	dd
    //   0	49	1	paramdb	db
    //   0	49	2	paramString	String
    //   0	49	3	paramcx	cx
  }
  
  public ArrayList<String> a(boolean paramBoolean)
  {
    return null;
  }
  
  /* Error */
  public void a(String arg1, cw arg2)
  {
    // Byte code:
    //   0: return
    //   1: astore_1
    //   2: return
  }
  
  public boolean b()
  {
    return false;
  }
}


/* Location:              C:\Users\adinb\Downloads\dex2jar-2.0\dex2jar-2.0\0x89a2c000-dex2jar.jar!\com\xiaomi\push\dd.class
 * Java compiler version: 6 (50.0)
 * JD-Core Version:       0.7.1
 */