package com.xiaomi.push;

import android.content.Context;
import android.content.SharedPreferences;
import android.content.SharedPreferences.Editor;
import java.io.File;

public class hk
{
  private static boolean a;
  
  private static void a(Context paramContext)
  {
    StringBuilder localStringBuilder = new StringBuilder();
    localStringBuilder.append(paramContext.getFilesDir());
    localStringBuilder.append("/tdReadTemp");
    paramContext = new File(localStringBuilder.toString());
    if (!paramContext.exists()) {
      paramContext.mkdirs();
    }
  }
  
  public static void a(Context paramContext, hn paramhn)
  {
    ai.a(paramContext).a(new a(paramContext, paramhn));
  }
  
  /* Error */
  private static void a(Context paramContext, hn paramhn, File paramFile, byte[] paramArrayOfByte)
  {
    // Byte code:
    //   0: new 64	java/util/ArrayList
    //   3: dup
    //   4: invokespecial 65	java/util/ArrayList:<init>	()V
    //   7: astore 11
    //   9: iconst_4
    //   10: newarray <illegal type>
    //   12: astore 12
    //   14: aconst_null
    //   15: astore 10
    //   17: aconst_null
    //   18: astore 8
    //   20: new 67	java/io/BufferedInputStream
    //   23: dup
    //   24: new 69	java/io/FileInputStream
    //   27: dup
    //   28: aload_2
    //   29: invokespecial 72	java/io/FileInputStream:<init>	(Ljava/io/File;)V
    //   32: invokespecial 75	java/io/BufferedInputStream:<init>	(Ljava/io/InputStream;)V
    //   35: astore 9
    //   37: aload 11
    //   39: astore 8
    //   41: iconst_0
    //   42: istore 5
    //   44: iconst_0
    //   45: istore 4
    //   47: aload 9
    //   49: aload 12
    //   51: invokevirtual 79	java/io/BufferedInputStream:read	([B)I
    //   54: istore 6
    //   56: iload 6
    //   58: iconst_m1
    //   59: if_icmpne +6 -> 65
    //   62: goto +322 -> 384
    //   65: iload 6
    //   67: iconst_4
    //   68: if_icmpeq +37 -> 105
    //   71: new 14	java/lang/StringBuilder
    //   74: dup
    //   75: invokespecial 17	java/lang/StringBuilder:<init>	()V
    //   78: astore_3
    //   79: aload_3
    //   80: ldc 81
    //   82: invokevirtual 32	java/lang/StringBuilder:append	(Ljava/lang/String;)Ljava/lang/StringBuilder;
    //   85: pop
    //   86: aload_3
    //   87: iload 6
    //   89: invokevirtual 84	java/lang/StringBuilder:append	(I)Ljava/lang/StringBuilder;
    //   92: pop
    //   93: aload_3
    //   94: invokevirtual 38	java/lang/StringBuilder:toString	()Ljava/lang/String;
    //   97: astore_3
    //   98: aload_3
    //   99: invokestatic 89	com/xiaomi/channel/commonutils/logger/b:d	(Ljava/lang/String;)V
    //   102: goto +282 -> 384
    //   105: aload 12
    //   107: invokestatic 93	com/xiaomi/push/ac:a	([B)I
    //   110: istore 6
    //   112: iload 6
    //   114: iconst_1
    //   115: if_icmplt +239 -> 354
    //   118: iload 6
    //   120: sipush 10240
    //   123: if_icmple +6 -> 129
    //   126: goto +228 -> 354
    //   129: iload 6
    //   131: newarray <illegal type>
    //   133: astore 10
    //   135: aload 9
    //   137: aload 10
    //   139: invokevirtual 79	java/io/BufferedInputStream:read	([B)I
    //   142: istore 7
    //   144: iload 7
    //   146: iload 6
    //   148: if_icmpeq +47 -> 195
    //   151: new 14	java/lang/StringBuilder
    //   154: dup
    //   155: invokespecial 17	java/lang/StringBuilder:<init>	()V
    //   158: astore_3
    //   159: aload_3
    //   160: ldc 95
    //   162: invokevirtual 32	java/lang/StringBuilder:append	(Ljava/lang/String;)Ljava/lang/StringBuilder;
    //   165: pop
    //   166: aload_3
    //   167: iload 7
    //   169: invokevirtual 84	java/lang/StringBuilder:append	(I)Ljava/lang/StringBuilder;
    //   172: pop
    //   173: aload_3
    //   174: ldc 97
    //   176: invokevirtual 32	java/lang/StringBuilder:append	(Ljava/lang/String;)Ljava/lang/StringBuilder;
    //   179: pop
    //   180: aload_3
    //   181: iload 6
    //   183: invokevirtual 84	java/lang/StringBuilder:append	(I)Ljava/lang/StringBuilder;
    //   186: pop
    //   187: aload_3
    //   188: invokevirtual 38	java/lang/StringBuilder:toString	()Ljava/lang/String;
    //   191: astore_3
    //   192: goto -94 -> 98
    //   195: aload_3
    //   196: aload 10
    //   198: invokestatic 102	com/xiaomi/push/h:a	([B[B)[B
    //   201: astore 10
    //   203: aload 10
    //   205: ifnull +141 -> 346
    //   208: aload 10
    //   210: arraylength
    //   211: ifne +6 -> 217
    //   214: goto +132 -> 346
    //   217: new 104	com/xiaomi/push/hs
    //   220: dup
    //   221: invokespecial 105	com/xiaomi/push/hs:<init>	()V
    //   224: astore 11
    //   226: aload 11
    //   228: aload 10
    //   230: invokestatic 110	com/xiaomi/push/iy:a	(Lcom/xiaomi/push/iz;[B)V
    //   233: aload 8
    //   235: aload 11
    //   237: invokevirtual 114	java/util/ArrayList:add	(Ljava/lang/Object;)Z
    //   240: pop
    //   241: iload 5
    //   243: iconst_1
    //   244: iadd
    //   245: istore 5
    //   247: iload 4
    //   249: aload 10
    //   251: arraylength
    //   252: iadd
    //   253: istore 6
    //   255: iload 5
    //   257: bipush 8
    //   259: if_icmpge +15 -> 274
    //   262: iload 6
    //   264: istore 4
    //   266: iload 6
    //   268: sipush 10240
    //   271: if_icmplt -224 -> 47
    //   274: new 14	java/lang/StringBuilder
    //   277: dup
    //   278: invokespecial 17	java/lang/StringBuilder:<init>	()V
    //   281: astore 10
    //   283: aload 10
    //   285: ldc 116
    //   287: invokevirtual 32	java/lang/StringBuilder:append	(Ljava/lang/String;)Ljava/lang/StringBuilder;
    //   290: pop
    //   291: aload 10
    //   293: aload 8
    //   295: invokevirtual 120	java/util/ArrayList:size	()I
    //   298: invokevirtual 84	java/lang/StringBuilder:append	(I)Ljava/lang/StringBuilder;
    //   301: pop
    //   302: aload 10
    //   304: ldc 122
    //   306: invokevirtual 32	java/lang/StringBuilder:append	(Ljava/lang/String;)Ljava/lang/StringBuilder;
    //   309: pop
    //   310: aload 10
    //   312: invokestatic 128	java/lang/System:currentTimeMillis	()J
    //   315: invokevirtual 131	java/lang/StringBuilder:append	(J)Ljava/lang/StringBuilder;
    //   318: pop
    //   319: aload 10
    //   321: invokevirtual 38	java/lang/StringBuilder:toString	()Ljava/lang/String;
    //   324: invokestatic 133	com/xiaomi/channel/commonutils/logger/b:a	(Ljava/lang/String;)V
    //   327: aload_0
    //   328: aload_1
    //   329: aload 8
    //   331: invokestatic 138	com/xiaomi/push/hl:a	(Landroid/content/Context;Lcom/xiaomi/push/hn;Ljava/util/List;)V
    //   334: new 64	java/util/ArrayList
    //   337: dup
    //   338: invokespecial 65	java/util/ArrayList:<init>	()V
    //   341: astore 8
    //   343: goto -302 -> 41
    //   346: ldc -116
    //   348: invokestatic 89	com/xiaomi/channel/commonutils/logger/b:d	(Ljava/lang/String;)V
    //   351: goto -304 -> 47
    //   354: new 14	java/lang/StringBuilder
    //   357: dup
    //   358: invokespecial 17	java/lang/StringBuilder:<init>	()V
    //   361: astore_3
    //   362: aload_3
    //   363: ldc -114
    //   365: invokevirtual 32	java/lang/StringBuilder:append	(Ljava/lang/String;)Ljava/lang/StringBuilder;
    //   368: pop
    //   369: aload_3
    //   370: iload 6
    //   372: invokevirtual 84	java/lang/StringBuilder:append	(I)Ljava/lang/StringBuilder;
    //   375: pop
    //   376: aload_3
    //   377: invokevirtual 38	java/lang/StringBuilder:toString	()Ljava/lang/String;
    //   380: astore_3
    //   381: goto -283 -> 98
    //   384: aload_0
    //   385: aload_1
    //   386: aload 8
    //   388: invokestatic 138	com/xiaomi/push/hl:a	(Landroid/content/Context;Lcom/xiaomi/push/hn;Ljava/util/List;)V
    //   391: new 14	java/lang/StringBuilder
    //   394: dup
    //   395: invokespecial 17	java/lang/StringBuilder:<init>	()V
    //   398: astore_0
    //   399: aload_0
    //   400: ldc -112
    //   402: invokevirtual 32	java/lang/StringBuilder:append	(Ljava/lang/String;)Ljava/lang/StringBuilder;
    //   405: pop
    //   406: aload_0
    //   407: aload 8
    //   409: invokevirtual 120	java/util/ArrayList:size	()I
    //   412: invokevirtual 84	java/lang/StringBuilder:append	(I)Ljava/lang/StringBuilder;
    //   415: pop
    //   416: aload_0
    //   417: ldc 122
    //   419: invokevirtual 32	java/lang/StringBuilder:append	(Ljava/lang/String;)Ljava/lang/StringBuilder;
    //   422: pop
    //   423: aload_0
    //   424: invokestatic 128	java/lang/System:currentTimeMillis	()J
    //   427: invokevirtual 131	java/lang/StringBuilder:append	(J)Ljava/lang/StringBuilder;
    //   430: pop
    //   431: aload_0
    //   432: invokevirtual 38	java/lang/StringBuilder:toString	()Ljava/lang/String;
    //   435: invokestatic 133	com/xiaomi/channel/commonutils/logger/b:a	(Ljava/lang/String;)V
    //   438: aload_2
    //   439: ifnull +22 -> 461
    //   442: aload_2
    //   443: invokevirtual 45	java/io/File:exists	()Z
    //   446: ifeq +15 -> 461
    //   449: aload_2
    //   450: invokevirtual 147	java/io/File:delete	()Z
    //   453: ifne +8 -> 461
    //   456: ldc -107
    //   458: invokestatic 133	com/xiaomi/channel/commonutils/logger/b:a	(Ljava/lang/String;)V
    //   461: aload 9
    //   463: invokestatic 154	com/xiaomi/push/y:a	(Ljava/io/Closeable;)V
    //   466: return
    //   467: astore_0
    //   468: aload 9
    //   470: astore 8
    //   472: goto +30 -> 502
    //   475: astore_1
    //   476: aload 9
    //   478: astore_0
    //   479: goto +11 -> 490
    //   482: astore_0
    //   483: goto +19 -> 502
    //   486: astore_1
    //   487: aload 10
    //   489: astore_0
    //   490: aload_0
    //   491: astore 8
    //   493: aload_1
    //   494: invokestatic 157	com/xiaomi/channel/commonutils/logger/b:a	(Ljava/lang/Throwable;)V
    //   497: aload_0
    //   498: invokestatic 154	com/xiaomi/push/y:a	(Ljava/io/Closeable;)V
    //   501: return
    //   502: aload 8
    //   504: invokestatic 154	com/xiaomi/push/y:a	(Ljava/io/Closeable;)V
    //   507: aload_0
    //   508: athrow
    // Local variable table:
    //   start	length	slot	name	signature
    //   0	509	0	paramContext	Context
    //   0	509	1	paramhn	hn
    //   0	509	2	paramFile	File
    //   0	509	3	paramArrayOfByte	byte[]
    //   45	220	4	i	int
    //   42	218	5	j	int
    //   54	317	6	k	int
    //   142	26	7	m	int
    //   18	485	8	localObject1	Object
    //   35	442	9	localBufferedInputStream	java.io.BufferedInputStream
    //   15	473	10	localObject2	Object
    //   7	229	11	localObject3	Object
    //   12	94	12	arrayOfByte	byte[]
    // Exception table:
    //   from	to	target	type
    //   47	56	467	finally
    //   71	98	467	finally
    //   98	102	467	finally
    //   105	112	467	finally
    //   129	144	467	finally
    //   151	192	467	finally
    //   195	203	467	finally
    //   208	214	467	finally
    //   217	241	467	finally
    //   247	255	467	finally
    //   274	343	467	finally
    //   346	351	467	finally
    //   354	381	467	finally
    //   384	438	467	finally
    //   442	461	467	finally
    //   47	56	475	java/lang/Exception
    //   71	98	475	java/lang/Exception
    //   98	102	475	java/lang/Exception
    //   105	112	475	java/lang/Exception
    //   129	144	475	java/lang/Exception
    //   151	192	475	java/lang/Exception
    //   195	203	475	java/lang/Exception
    //   208	214	475	java/lang/Exception
    //   217	241	475	java/lang/Exception
    //   247	255	475	java/lang/Exception
    //   274	343	475	java/lang/Exception
    //   346	351	475	java/lang/Exception
    //   354	381	475	java/lang/Exception
    //   384	438	475	java/lang/Exception
    //   442	461	475	java/lang/Exception
    //   20	37	482	finally
    //   493	497	482	finally
    //   20	37	486	java/lang/Exception
  }
  
  private static void b(Context paramContext)
  {
    paramContext = paramContext.getSharedPreferences("mipush_extra", 4).edit();
    paramContext.putLong("last_tiny_data_upload_timestamp", System.currentTimeMillis() / 1000L);
    paramContext.commit();
  }
  
  /* Error */
  private static void c(Context paramContext, hn paramhn)
  {
    // Byte code:
    //   0: getstatic 190	com/xiaomi/push/hk:a	Z
    //   3: ifne +438 -> 441
    //   6: iconst_1
    //   7: putstatic 190	com/xiaomi/push/hk:a	Z
    //   10: new 34	java/io/File
    //   13: dup
    //   14: aload_0
    //   15: invokevirtual 23	android/content/Context:getFilesDir	()Ljava/io/File;
    //   18: ldc -64
    //   20: invokespecial 195	java/io/File:<init>	(Ljava/io/File;Ljava/lang/String;)V
    //   23: astore 8
    //   25: aload 8
    //   27: invokevirtual 45	java/io/File:exists	()Z
    //   30: ifne +9 -> 39
    //   33: ldc -59
    //   35: invokestatic 133	com/xiaomi/channel/commonutils/logger/b:a	(Ljava/lang/String;)V
    //   38: return
    //   39: aload_0
    //   40: invokestatic 199	com/xiaomi/push/hk:a	(Landroid/content/Context;)V
    //   43: aload_0
    //   44: invokestatic 204	com/xiaomi/push/service/bg:a	(Landroid/content/Context;)[B
    //   47: astore 7
    //   49: aconst_null
    //   50: astore 5
    //   52: aconst_null
    //   53: astore 4
    //   55: aconst_null
    //   56: astore_3
    //   57: aconst_null
    //   58: astore 6
    //   60: new 34	java/io/File
    //   63: dup
    //   64: aload_0
    //   65: invokevirtual 23	android/content/Context:getFilesDir	()Ljava/io/File;
    //   68: ldc -50
    //   70: invokespecial 195	java/io/File:<init>	(Ljava/io/File;Ljava/lang/String;)V
    //   73: astore_2
    //   74: aload_2
    //   75: invokestatic 209	com/xiaomi/push/y:a	(Ljava/io/File;)Z
    //   78: pop
    //   79: new 211	java/io/RandomAccessFile
    //   82: dup
    //   83: aload_2
    //   84: ldc -43
    //   86: invokespecial 214	java/io/RandomAccessFile:<init>	(Ljava/io/File;Ljava/lang/String;)V
    //   89: astore_2
    //   90: aload 6
    //   92: astore 5
    //   94: aload 4
    //   96: astore_3
    //   97: aload_2
    //   98: astore 4
    //   100: aload_2
    //   101: invokevirtual 218	java/io/RandomAccessFile:getChannel	()Ljava/nio/channels/FileChannel;
    //   104: invokevirtual 224	java/nio/channels/FileChannel:lock	()Ljava/nio/channels/FileLock;
    //   107: astore 6
    //   109: aload 6
    //   111: astore 5
    //   113: aload 6
    //   115: astore_3
    //   116: aload_2
    //   117: astore 4
    //   119: new 14	java/lang/StringBuilder
    //   122: dup
    //   123: invokespecial 17	java/lang/StringBuilder:<init>	()V
    //   126: astore 9
    //   128: aload 6
    //   130: astore 5
    //   132: aload 6
    //   134: astore_3
    //   135: aload_2
    //   136: astore 4
    //   138: aload 9
    //   140: aload_0
    //   141: invokevirtual 23	android/content/Context:getFilesDir	()Ljava/io/File;
    //   144: invokevirtual 27	java/lang/StringBuilder:append	(Ljava/lang/Object;)Ljava/lang/StringBuilder;
    //   147: pop
    //   148: aload 6
    //   150: astore 5
    //   152: aload 6
    //   154: astore_3
    //   155: aload_2
    //   156: astore 4
    //   158: aload 9
    //   160: ldc 29
    //   162: invokevirtual 32	java/lang/StringBuilder:append	(Ljava/lang/String;)Ljava/lang/StringBuilder;
    //   165: pop
    //   166: aload 6
    //   168: astore 5
    //   170: aload 6
    //   172: astore_3
    //   173: aload_2
    //   174: astore 4
    //   176: aload 9
    //   178: ldc -30
    //   180: invokevirtual 32	java/lang/StringBuilder:append	(Ljava/lang/String;)Ljava/lang/StringBuilder;
    //   183: pop
    //   184: aload 6
    //   186: astore 5
    //   188: aload 6
    //   190: astore_3
    //   191: aload_2
    //   192: astore 4
    //   194: aload 9
    //   196: ldc -64
    //   198: invokevirtual 32	java/lang/StringBuilder:append	(Ljava/lang/String;)Ljava/lang/StringBuilder;
    //   201: pop
    //   202: aload 6
    //   204: astore 5
    //   206: aload 6
    //   208: astore_3
    //   209: aload_2
    //   210: astore 4
    //   212: aload 8
    //   214: new 34	java/io/File
    //   217: dup
    //   218: aload 9
    //   220: invokevirtual 38	java/lang/StringBuilder:toString	()Ljava/lang/String;
    //   223: invokespecial 41	java/io/File:<init>	(Ljava/lang/String;)V
    //   226: invokevirtual 229	java/io/File:renameTo	(Ljava/io/File;)Z
    //   229: pop
    //   230: aload_2
    //   231: astore_3
    //   232: aload 6
    //   234: ifnull +88 -> 322
    //   237: aload_2
    //   238: astore_3
    //   239: aload 6
    //   241: invokevirtual 234	java/nio/channels/FileLock:isValid	()Z
    //   244: ifeq +78 -> 322
    //   247: aload 6
    //   249: invokevirtual 237	java/nio/channels/FileLock:release	()V
    //   252: aload_2
    //   253: astore_3
    //   254: goto +68 -> 322
    //   257: astore_3
    //   258: goto +58 -> 316
    //   261: astore 6
    //   263: goto +14 -> 277
    //   266: astore_0
    //   267: aconst_null
    //   268: astore 4
    //   270: goto +141 -> 411
    //   273: astore 6
    //   275: aconst_null
    //   276: astore_2
    //   277: aload 5
    //   279: astore_3
    //   280: aload_2
    //   281: astore 4
    //   283: aload 6
    //   285: invokestatic 157	com/xiaomi/channel/commonutils/logger/b:a	(Ljava/lang/Throwable;)V
    //   288: aload_2
    //   289: astore_3
    //   290: aload 5
    //   292: ifnull +30 -> 322
    //   295: aload_2
    //   296: astore_3
    //   297: aload 5
    //   299: invokevirtual 234	java/nio/channels/FileLock:isValid	()Z
    //   302: ifeq +20 -> 322
    //   305: aload 5
    //   307: invokevirtual 237	java/nio/channels/FileLock:release	()V
    //   310: aload_2
    //   311: astore_3
    //   312: goto +10 -> 322
    //   315: astore_3
    //   316: aload_3
    //   317: invokestatic 157	com/xiaomi/channel/commonutils/logger/b:a	(Ljava/lang/Throwable;)V
    //   320: aload_2
    //   321: astore_3
    //   322: aload_3
    //   323: invokestatic 154	com/xiaomi/push/y:a	(Ljava/io/Closeable;)V
    //   326: new 14	java/lang/StringBuilder
    //   329: dup
    //   330: invokespecial 17	java/lang/StringBuilder:<init>	()V
    //   333: astore_2
    //   334: aload_2
    //   335: aload_0
    //   336: invokevirtual 23	android/content/Context:getFilesDir	()Ljava/io/File;
    //   339: invokevirtual 27	java/lang/StringBuilder:append	(Ljava/lang/Object;)Ljava/lang/StringBuilder;
    //   342: pop
    //   343: aload_2
    //   344: ldc 29
    //   346: invokevirtual 32	java/lang/StringBuilder:append	(Ljava/lang/String;)Ljava/lang/StringBuilder;
    //   349: pop
    //   350: aload_2
    //   351: ldc -30
    //   353: invokevirtual 32	java/lang/StringBuilder:append	(Ljava/lang/String;)Ljava/lang/StringBuilder;
    //   356: pop
    //   357: aload_2
    //   358: ldc -64
    //   360: invokevirtual 32	java/lang/StringBuilder:append	(Ljava/lang/String;)Ljava/lang/StringBuilder;
    //   363: pop
    //   364: new 34	java/io/File
    //   367: dup
    //   368: aload_2
    //   369: invokevirtual 38	java/lang/StringBuilder:toString	()Ljava/lang/String;
    //   372: invokespecial 41	java/io/File:<init>	(Ljava/lang/String;)V
    //   375: astore_2
    //   376: aload_2
    //   377: invokevirtual 45	java/io/File:exists	()Z
    //   380: ifne +9 -> 389
    //   383: ldc -59
    //   385: invokestatic 133	com/xiaomi/channel/commonutils/logger/b:a	(Ljava/lang/String;)V
    //   388: return
    //   389: aload_0
    //   390: aload_1
    //   391: aload_2
    //   392: aload 7
    //   394: invokestatic 239	com/xiaomi/push/hk:a	(Landroid/content/Context;Lcom/xiaomi/push/hn;Ljava/io/File;[B)V
    //   397: iconst_0
    //   398: invokestatic 244	com/xiaomi/push/hj:a	(Z)V
    //   401: aload_0
    //   402: invokestatic 246	com/xiaomi/push/hk:b	(Landroid/content/Context;)V
    //   405: iconst_0
    //   406: putstatic 190	com/xiaomi/push/hk:a	Z
    //   409: return
    //   410: astore_0
    //   411: aload_3
    //   412: ifnull +22 -> 434
    //   415: aload_3
    //   416: invokevirtual 234	java/nio/channels/FileLock:isValid	()Z
    //   419: ifeq +15 -> 434
    //   422: aload_3
    //   423: invokevirtual 237	java/nio/channels/FileLock:release	()V
    //   426: goto +8 -> 434
    //   429: astore_1
    //   430: aload_1
    //   431: invokestatic 157	com/xiaomi/channel/commonutils/logger/b:a	(Ljava/lang/Throwable;)V
    //   434: aload 4
    //   436: invokestatic 154	com/xiaomi/push/y:a	(Ljava/io/Closeable;)V
    //   439: aload_0
    //   440: athrow
    //   441: ldc -8
    //   443: invokestatic 133	com/xiaomi/channel/commonutils/logger/b:a	(Ljava/lang/String;)V
    //   446: return
    // Local variable table:
    //   start	length	slot	name	signature
    //   0	447	0	paramContext	Context
    //   0	447	1	paramhn	hn
    //   73	319	2	localObject1	Object
    //   56	198	3	localObject2	Object
    //   257	1	3	localIOException1	java.io.IOException
    //   279	33	3	localObject3	Object
    //   315	2	3	localIOException2	java.io.IOException
    //   321	102	3	localObject4	Object
    //   53	382	4	localObject5	Object
    //   50	256	5	localObject6	Object
    //   58	190	6	localFileLock	java.nio.channels.FileLock
    //   261	1	6	localException1	Exception
    //   273	11	6	localException2	Exception
    //   47	346	7	arrayOfByte	byte[]
    //   23	190	8	localFile	File
    //   126	93	9	localStringBuilder	StringBuilder
    // Exception table:
    //   from	to	target	type
    //   247	252	257	java/io/IOException
    //   100	109	261	java/lang/Exception
    //   119	128	261	java/lang/Exception
    //   138	148	261	java/lang/Exception
    //   158	166	261	java/lang/Exception
    //   176	184	261	java/lang/Exception
    //   194	202	261	java/lang/Exception
    //   212	230	261	java/lang/Exception
    //   60	90	266	finally
    //   60	90	273	java/lang/Exception
    //   305	310	315	java/io/IOException
    //   100	109	410	finally
    //   119	128	410	finally
    //   138	148	410	finally
    //   158	166	410	finally
    //   176	184	410	finally
    //   194	202	410	finally
    //   212	230	410	finally
    //   283	288	410	finally
    //   422	426	429	java/io/IOException
  }
  
  static class a
    implements Runnable
  {
    private Context jdField_a_of_type_AndroidContentContext;
    private hn jdField_a_of_type_ComXiaomiPushHn;
    
    public a(Context paramContext, hn paramhn)
    {
      this.jdField_a_of_type_ComXiaomiPushHn = paramhn;
      this.jdField_a_of_type_AndroidContentContext = paramContext;
    }
    
    public void run()
    {
      hk.b(this.jdField_a_of_type_AndroidContentContext, this.jdField_a_of_type_ComXiaomiPushHn);
    }
  }
}


/* Location:              C:\Users\adinb\Downloads\dex2jar-2.0\dex2jar-2.0\0x89a2c000-dex2jar.jar!\com\xiaomi\push\hk.class
 * Java compiler version: 6 (50.0)
 * JD-Core Version:       0.7.1
 */