package com.facebook.imageutils;

import android.util.Pair;
import java.io.IOException;
import java.io.InputStream;
import javax.annotation.Nullable;

public class WebpUtil
{
  private static final String VP8L_HEADER = "VP8L";
  private static final String VP8X_HEADER = "VP8X";
  private static final String VP8_HEADER = "VP8 ";
  
  private static boolean compare(byte[] paramArrayOfByte, String paramString)
  {
    if (paramArrayOfByte.length != paramString.length()) {
      return false;
    }
    int i = 0;
    while (i < paramArrayOfByte.length)
    {
      if (paramString.charAt(i) != paramArrayOfByte[i]) {
        return false;
      }
      i += 1;
    }
    return true;
  }
  
  public static int get2BytesAsInt(InputStream paramInputStream)
    throws IOException
  {
    int i = (byte)paramInputStream.read();
    return (byte)paramInputStream.read() << 8 & 0xFF00 | i & 0xFF;
  }
  
  private static byte getByte(InputStream paramInputStream)
    throws IOException
  {
    return (byte)(paramInputStream.read() & 0xFF);
  }
  
  private static String getHeader(byte[] paramArrayOfByte)
  {
    StringBuilder localStringBuilder = new StringBuilder();
    int i = 0;
    while (i < paramArrayOfByte.length)
    {
      localStringBuilder.append((char)paramArrayOfByte[i]);
      i += 1;
    }
    return localStringBuilder.toString();
  }
  
  private static int getInt(InputStream paramInputStream)
    throws IOException
  {
    int i = (byte)paramInputStream.read();
    int j = (byte)paramInputStream.read();
    int k = (byte)paramInputStream.read();
    return (byte)paramInputStream.read() << 24 & 0xFF000000 | k << 16 & 0xFF0000 | j << 8 & 0xFF00 | i & 0xFF;
  }
  
  private static short getShort(InputStream paramInputStream)
    throws IOException
  {
    return (short)(paramInputStream.read() & 0xFF);
  }
  
  /* Error */
  @Nullable
  public static Pair<Integer, Integer> getSize(InputStream paramInputStream)
  {
    // Byte code:
    //   0: iconst_4
    //   1: newarray <illegal type>
    //   3: astore_2
    //   4: aload_0
    //   5: aload_2
    //   6: invokevirtual 68	java/io/InputStream:read	([B)I
    //   9: pop
    //   10: aload_2
    //   11: ldc 70
    //   13: invokestatic 72	com/facebook/imageutils/WebpUtil:compare	([BLjava/lang/String;)Z
    //   16: istore_1
    //   17: iload_1
    //   18: ifne +20 -> 38
    //   21: aload_0
    //   22: ifnull +14 -> 36
    //   25: aload_0
    //   26: invokevirtual 75	java/io/InputStream:close	()V
    //   29: aconst_null
    //   30: areturn
    //   31: astore_0
    //   32: aload_0
    //   33: invokevirtual 78	java/io/IOException:printStackTrace	()V
    //   36: aconst_null
    //   37: areturn
    //   38: aload_0
    //   39: invokestatic 80	com/facebook/imageutils/WebpUtil:getInt	(Ljava/io/InputStream;)I
    //   42: pop
    //   43: aload_0
    //   44: aload_2
    //   45: invokevirtual 68	java/io/InputStream:read	([B)I
    //   48: pop
    //   49: aload_2
    //   50: ldc 82
    //   52: invokestatic 72	com/facebook/imageutils/WebpUtil:compare	([BLjava/lang/String;)Z
    //   55: istore_1
    //   56: iload_1
    //   57: ifne +20 -> 77
    //   60: aload_0
    //   61: ifnull +14 -> 75
    //   64: aload_0
    //   65: invokevirtual 75	java/io/InputStream:close	()V
    //   68: aconst_null
    //   69: areturn
    //   70: astore_0
    //   71: aload_0
    //   72: invokevirtual 78	java/io/IOException:printStackTrace	()V
    //   75: aconst_null
    //   76: areturn
    //   77: aload_0
    //   78: aload_2
    //   79: invokevirtual 68	java/io/InputStream:read	([B)I
    //   82: pop
    //   83: aload_2
    //   84: invokestatic 84	com/facebook/imageutils/WebpUtil:getHeader	([B)Ljava/lang/String;
    //   87: astore_2
    //   88: ldc 14
    //   90: aload_2
    //   91: invokevirtual 88	java/lang/String:equals	(Ljava/lang/Object;)Z
    //   94: ifeq +25 -> 119
    //   97: aload_0
    //   98: invokestatic 91	com/facebook/imageutils/WebpUtil:getVP8Dimension	(Ljava/io/InputStream;)Landroid/util/Pair;
    //   101: astore_2
    //   102: aload_0
    //   103: ifnull +14 -> 117
    //   106: aload_0
    //   107: invokevirtual 75	java/io/InputStream:close	()V
    //   110: aload_2
    //   111: areturn
    //   112: astore_0
    //   113: aload_0
    //   114: invokevirtual 78	java/io/IOException:printStackTrace	()V
    //   117: aload_2
    //   118: areturn
    //   119: ldc 8
    //   121: aload_2
    //   122: invokevirtual 88	java/lang/String:equals	(Ljava/lang/Object;)Z
    //   125: ifeq +25 -> 150
    //   128: aload_0
    //   129: invokestatic 94	com/facebook/imageutils/WebpUtil:getVP8LDimension	(Ljava/io/InputStream;)Landroid/util/Pair;
    //   132: astore_2
    //   133: aload_0
    //   134: ifnull +14 -> 148
    //   137: aload_0
    //   138: invokevirtual 75	java/io/InputStream:close	()V
    //   141: aload_2
    //   142: areturn
    //   143: astore_0
    //   144: aload_0
    //   145: invokevirtual 78	java/io/IOException:printStackTrace	()V
    //   148: aload_2
    //   149: areturn
    //   150: ldc 11
    //   152: aload_2
    //   153: invokevirtual 88	java/lang/String:equals	(Ljava/lang/Object;)Z
    //   156: ifeq +25 -> 181
    //   159: aload_0
    //   160: invokestatic 97	com/facebook/imageutils/WebpUtil:getVP8XDimension	(Ljava/io/InputStream;)Landroid/util/Pair;
    //   163: astore_2
    //   164: aload_0
    //   165: ifnull +14 -> 179
    //   168: aload_0
    //   169: invokevirtual 75	java/io/InputStream:close	()V
    //   172: aload_2
    //   173: areturn
    //   174: astore_0
    //   175: aload_0
    //   176: invokevirtual 78	java/io/IOException:printStackTrace	()V
    //   179: aload_2
    //   180: areturn
    //   181: aload_0
    //   182: ifnull +33 -> 215
    //   185: aload_0
    //   186: invokevirtual 75	java/io/InputStream:close	()V
    //   189: aconst_null
    //   190: areturn
    //   191: astore_2
    //   192: goto +25 -> 217
    //   195: astore_2
    //   196: aload_2
    //   197: invokevirtual 78	java/io/IOException:printStackTrace	()V
    //   200: aload_0
    //   201: ifnull +14 -> 215
    //   204: aload_0
    //   205: invokevirtual 75	java/io/InputStream:close	()V
    //   208: aconst_null
    //   209: areturn
    //   210: astore_0
    //   211: aload_0
    //   212: invokevirtual 78	java/io/IOException:printStackTrace	()V
    //   215: aconst_null
    //   216: areturn
    //   217: aload_0
    //   218: ifnull +15 -> 233
    //   221: aload_0
    //   222: invokevirtual 75	java/io/InputStream:close	()V
    //   225: goto +8 -> 233
    //   228: astore_0
    //   229: aload_0
    //   230: invokevirtual 78	java/io/IOException:printStackTrace	()V
    //   233: aload_2
    //   234: athrow
    // Local variable table:
    //   start	length	slot	name	signature
    //   0	235	0	paramInputStream	InputStream
    //   16	41	1	bool	boolean
    //   3	177	2	localObject1	Object
    //   191	1	2	localObject2	Object
    //   195	39	2	localIOException	IOException
    // Exception table:
    //   from	to	target	type
    //   25	29	31	java/io/IOException
    //   64	68	70	java/io/IOException
    //   106	110	112	java/io/IOException
    //   137	141	143	java/io/IOException
    //   168	172	174	java/io/IOException
    //   4	17	191	finally
    //   38	56	191	finally
    //   77	102	191	finally
    //   119	133	191	finally
    //   150	164	191	finally
    //   196	200	191	finally
    //   4	17	195	java/io/IOException
    //   38	56	195	java/io/IOException
    //   77	102	195	java/io/IOException
    //   119	133	195	java/io/IOException
    //   150	164	195	java/io/IOException
    //   185	189	210	java/io/IOException
    //   204	208	210	java/io/IOException
    //   221	225	228	java/io/IOException
  }
  
  @Nullable
  private static Pair<Integer, Integer> getVP8Dimension(InputStream paramInputStream)
    throws IOException
  {
    paramInputStream.skip(7L);
    int i = getShort(paramInputStream);
    int j = getShort(paramInputStream);
    int k = getShort(paramInputStream);
    if ((i == 157) && (j == 1) && (k == 42)) {
      return new Pair(Integer.valueOf(get2BytesAsInt(paramInputStream)), Integer.valueOf(get2BytesAsInt(paramInputStream)));
    }
    return null;
  }
  
  @Nullable
  private static Pair<Integer, Integer> getVP8LDimension(InputStream paramInputStream)
    throws IOException
  {
    getInt(paramInputStream);
    if (getByte(paramInputStream) != 47) {
      return null;
    }
    int i = (byte)paramInputStream.read();
    int j = (byte)paramInputStream.read() & 0xFF;
    int k = (byte)paramInputStream.read();
    return new Pair(Integer.valueOf((i & 0xFF | (j & 0x3F) << 8) + 1), Integer.valueOf((((byte)paramInputStream.read() & 0xFF & 0xF) << 10 | (k & 0xFF) << 2 | (j & 0xC0) >> 6) + 1));
  }
  
  private static Pair<Integer, Integer> getVP8XDimension(InputStream paramInputStream)
    throws IOException
  {
    paramInputStream.skip(8L);
    return new Pair(Integer.valueOf(read3Bytes(paramInputStream) + 1), Integer.valueOf(read3Bytes(paramInputStream) + 1));
  }
  
  private static boolean isBitOne(byte paramByte, int paramInt)
  {
    return (paramByte >> paramInt % 8 & 0x1) == 1;
  }
  
  private static int read3Bytes(InputStream paramInputStream)
    throws IOException
  {
    int i = getByte(paramInputStream);
    int j = getByte(paramInputStream);
    return getByte(paramInputStream) << 16 & 0xFF0000 | j << 8 & 0xFF00 | i & 0xFF;
  }
}


/* Location:              C:\Users\adinb\Downloads\dex2jar-2.0\dex2jar-2.0\0x89a2c000-dex2jar.jar!\com\facebook\imageutils\WebpUtil.class
 * Java compiler version: 6 (50.0)
 * JD-Core Version:       0.7.1
 */