package com.google.android.gms.measurement.internal;

import android.content.Context;
import android.database.Cursor;
import android.database.sqlite.SQLiteDatabase;
import android.database.sqlite.SQLiteException;
import android.os.Parcel;
import java.io.File;

public final class zzen
  extends zzg
{
  private final zzem zza = new zzem(this, zzm(), "google_app_measurement_local.db");
  private boolean zzb;
  
  zzen(zzfv paramzzfv)
  {
    super(paramzzfv);
  }
  
  private static long zza(SQLiteDatabase paramSQLiteDatabase)
  {
    SQLiteDatabase localSQLiteDatabase = null;
    try
    {
      paramSQLiteDatabase = paramSQLiteDatabase.query("messages", new String[] { "rowid" }, "type=?", new String[] { "3" }, null, null, "rowid desc", "1");
      localSQLiteDatabase = paramSQLiteDatabase;
      if (paramSQLiteDatabase.moveToFirst())
      {
        localSQLiteDatabase = paramSQLiteDatabase;
        long l = paramSQLiteDatabase.getLong(0);
        return l;
      }
      return -1L;
    }
    finally
    {
      if (localSQLiteDatabase != null) {
        localSQLiteDatabase.close();
      }
    }
  }
  
  /* Error */
  private final boolean zza(int paramInt, byte[] paramArrayOfByte)
  {
    // Byte code:
    //   0: aload_0
    //   1: invokevirtual 75	com/google/android/gms/measurement/internal/zzgo:zzc	()V
    //   4: aload_0
    //   5: getfield 77	com/google/android/gms/measurement/internal/zzen:zzb	Z
    //   8: ifeq +5 -> 13
    //   11: iconst_0
    //   12: ireturn
    //   13: new 79	android/content/ContentValues
    //   16: dup
    //   17: invokespecial 81	android/content/ContentValues:<init>	()V
    //   20: astore 15
    //   22: aload 15
    //   24: ldc 83
    //   26: iload_1
    //   27: invokestatic 89	java/lang/Integer:valueOf	(I)Ljava/lang/Integer;
    //   30: invokevirtual 93	android/content/ContentValues:put	(Ljava/lang/String;Ljava/lang/Integer;)V
    //   33: aload 15
    //   35: ldc 95
    //   37: aload_2
    //   38: invokevirtual 98	android/content/ContentValues:put	(Ljava/lang/String;[B)V
    //   41: iconst_0
    //   42: istore_3
    //   43: iconst_5
    //   44: istore 4
    //   46: iload_3
    //   47: iconst_5
    //   48: if_icmpge +541 -> 589
    //   51: aconst_null
    //   52: astore 13
    //   54: aconst_null
    //   55: astore 12
    //   57: aconst_null
    //   58: astore 14
    //   60: aconst_null
    //   61: astore 10
    //   63: aconst_null
    //   64: astore 9
    //   66: aload_0
    //   67: invokespecial 102	com/google/android/gms/measurement/internal/zzen:zzad	()Landroid/database/sqlite/SQLiteDatabase;
    //   70: astore_2
    //   71: aload_2
    //   72: ifnonnull +25 -> 97
    //   75: aload 14
    //   77: astore 9
    //   79: aload_2
    //   80: astore 11
    //   82: aload_0
    //   83: iconst_1
    //   84: putfield 77	com/google/android/gms/measurement/internal/zzen:zzb	Z
    //   87: aload_2
    //   88: ifnull +7 -> 95
    //   91: aload_2
    //   92: invokevirtual 103	android/database/sqlite/SQLiteDatabase:close	()V
    //   95: iconst_0
    //   96: ireturn
    //   97: aload 14
    //   99: astore 9
    //   101: aload_2
    //   102: astore 11
    //   104: aload_2
    //   105: invokevirtual 106	android/database/sqlite/SQLiteDatabase:beginTransaction	()V
    //   108: lconst_0
    //   109: lstore 7
    //   111: aload 14
    //   113: astore 9
    //   115: aload_2
    //   116: astore 11
    //   118: aload_2
    //   119: ldc 108
    //   121: aconst_null
    //   122: invokevirtual 112	android/database/sqlite/SQLiteDatabase:rawQuery	(Ljava/lang/String;[Ljava/lang/String;)Landroid/database/Cursor;
    //   125: astore 10
    //   127: lload 7
    //   129: lstore 5
    //   131: aload 10
    //   133: ifnull +53 -> 186
    //   136: lload 7
    //   138: lstore 5
    //   140: aload 10
    //   142: invokeinterface 55 1 0
    //   147: ifeq +39 -> 186
    //   150: aload 10
    //   152: iconst_0
    //   153: invokeinterface 59 2 0
    //   158: lstore 5
    //   160: goto +26 -> 186
    //   163: astore 9
    //   165: goto +253 -> 418
    //   168: astore 9
    //   170: goto +156 -> 326
    //   173: astore 9
    //   175: aload 10
    //   177: astore 12
    //   179: aload 9
    //   181: astore 10
    //   183: goto +301 -> 484
    //   186: lload 5
    //   188: ldc2_w 113
    //   191: lcmp
    //   192: iflt +86 -> 278
    //   195: aload_0
    //   196: invokevirtual 118	com/google/android/gms/measurement/internal/zzgo:zzq	()Lcom/google/android/gms/measurement/internal/zzer;
    //   199: invokevirtual 124	com/google/android/gms/measurement/internal/zzer:zze	()Lcom/google/android/gms/measurement/internal/zzet;
    //   202: ldc 126
    //   204: invokevirtual 131	com/google/android/gms/measurement/internal/zzet:zza	(Ljava/lang/String;)V
    //   207: ldc2_w 113
    //   210: lload 5
    //   212: lsub
    //   213: lconst_1
    //   214: ladd
    //   215: lstore 5
    //   217: aload_2
    //   218: ldc 31
    //   220: ldc -123
    //   222: iconst_1
    //   223: anewarray 33	java/lang/String
    //   226: dup
    //   227: iconst_0
    //   228: lload 5
    //   230: invokestatic 139	java/lang/Long:toString	(J)Ljava/lang/String;
    //   233: aastore
    //   234: invokevirtual 143	android/database/sqlite/SQLiteDatabase:delete	(Ljava/lang/String;Ljava/lang/String;[Ljava/lang/String;)I
    //   237: i2l
    //   238: lstore 7
    //   240: lload 7
    //   242: lload 5
    //   244: lcmp
    //   245: ifeq +33 -> 278
    //   248: aload_0
    //   249: invokevirtual 118	com/google/android/gms/measurement/internal/zzgo:zzq	()Lcom/google/android/gms/measurement/internal/zzer;
    //   252: invokevirtual 124	com/google/android/gms/measurement/internal/zzer:zze	()Lcom/google/android/gms/measurement/internal/zzet;
    //   255: ldc -111
    //   257: lload 5
    //   259: invokestatic 148	java/lang/Long:valueOf	(J)Ljava/lang/Long;
    //   262: lload 7
    //   264: invokestatic 148	java/lang/Long:valueOf	(J)Ljava/lang/Long;
    //   267: lload 5
    //   269: lload 7
    //   271: lsub
    //   272: invokestatic 148	java/lang/Long:valueOf	(J)Ljava/lang/Long;
    //   275: invokevirtual 151	com/google/android/gms/measurement/internal/zzet:zza	(Ljava/lang/String;Ljava/lang/Object;Ljava/lang/Object;Ljava/lang/Object;)V
    //   278: aload_2
    //   279: ldc 31
    //   281: aconst_null
    //   282: aload 15
    //   284: invokevirtual 155	android/database/sqlite/SQLiteDatabase:insertOrThrow	(Ljava/lang/String;Ljava/lang/String;Landroid/content/ContentValues;)J
    //   287: pop2
    //   288: aload_2
    //   289: invokevirtual 158	android/database/sqlite/SQLiteDatabase:setTransactionSuccessful	()V
    //   292: aload_2
    //   293: invokevirtual 161	android/database/sqlite/SQLiteDatabase:endTransaction	()V
    //   296: aload 10
    //   298: ifnull +10 -> 308
    //   301: aload 10
    //   303: invokeinterface 63 1 0
    //   308: aload_2
    //   309: ifnull +7 -> 316
    //   312: aload_2
    //   313: invokevirtual 103	android/database/sqlite/SQLiteDatabase:close	()V
    //   316: iconst_1
    //   317: ireturn
    //   318: goto +109 -> 427
    //   321: astore 9
    //   323: aconst_null
    //   324: astore 10
    //   326: goto +27 -> 353
    //   329: astore 10
    //   331: goto +153 -> 484
    //   334: astore 9
    //   336: aconst_null
    //   337: astore_2
    //   338: goto +228 -> 566
    //   341: astore 11
    //   343: aconst_null
    //   344: astore 10
    //   346: aload 9
    //   348: astore_2
    //   349: aload 11
    //   351: astore 9
    //   353: aload_2
    //   354: ifnull +14 -> 368
    //   357: aload_2
    //   358: invokevirtual 164	android/database/sqlite/SQLiteDatabase:inTransaction	()Z
    //   361: ifeq +7 -> 368
    //   364: aload_2
    //   365: invokevirtual 161	android/database/sqlite/SQLiteDatabase:endTransaction	()V
    //   368: aload_0
    //   369: invokevirtual 118	com/google/android/gms/measurement/internal/zzgo:zzq	()Lcom/google/android/gms/measurement/internal/zzer;
    //   372: invokevirtual 124	com/google/android/gms/measurement/internal/zzer:zze	()Lcom/google/android/gms/measurement/internal/zzet;
    //   375: ldc -90
    //   377: aload 9
    //   379: invokevirtual 169	com/google/android/gms/measurement/internal/zzet:zza	(Ljava/lang/String;Ljava/lang/Object;)V
    //   382: aload_0
    //   383: iconst_1
    //   384: putfield 77	com/google/android/gms/measurement/internal/zzen:zzb	Z
    //   387: aload 10
    //   389: ifnull +10 -> 399
    //   392: aload 10
    //   394: invokeinterface 63 1 0
    //   399: iload 4
    //   401: istore_1
    //   402: aload_2
    //   403: ifnull +140 -> 543
    //   406: aload_2
    //   407: invokevirtual 103	android/database/sqlite/SQLiteDatabase:close	()V
    //   410: iload 4
    //   412: istore_1
    //   413: goto +130 -> 543
    //   416: astore 9
    //   418: goto +148 -> 566
    //   421: aconst_null
    //   422: astore_2
    //   423: aload 13
    //   425: astore 10
    //   427: iload 4
    //   429: i2l
    //   430: lstore 5
    //   432: aload 10
    //   434: astore 9
    //   436: aload_2
    //   437: astore 11
    //   439: lload 5
    //   441: invokestatic 175	android/os/SystemClock:sleep	(J)V
    //   444: iload 4
    //   446: bipush 20
    //   448: iadd
    //   449: istore 4
    //   451: aload 10
    //   453: ifnull +10 -> 463
    //   456: aload 10
    //   458: invokeinterface 63 1 0
    //   463: iload 4
    //   465: istore_1
    //   466: aload_2
    //   467: ifnull +76 -> 543
    //   470: aload_2
    //   471: invokevirtual 103	android/database/sqlite/SQLiteDatabase:close	()V
    //   474: iload 4
    //   476: istore_1
    //   477: goto +66 -> 543
    //   480: astore 10
    //   482: aconst_null
    //   483: astore_2
    //   484: aload 12
    //   486: astore 9
    //   488: aload_2
    //   489: astore 11
    //   491: aload_0
    //   492: invokevirtual 118	com/google/android/gms/measurement/internal/zzgo:zzq	()Lcom/google/android/gms/measurement/internal/zzer;
    //   495: invokevirtual 124	com/google/android/gms/measurement/internal/zzer:zze	()Lcom/google/android/gms/measurement/internal/zzet;
    //   498: ldc -79
    //   500: aload 10
    //   502: invokevirtual 169	com/google/android/gms/measurement/internal/zzet:zza	(Ljava/lang/String;Ljava/lang/Object;)V
    //   505: aload 12
    //   507: astore 9
    //   509: aload_2
    //   510: astore 11
    //   512: aload_0
    //   513: iconst_1
    //   514: putfield 77	com/google/android/gms/measurement/internal/zzen:zzb	Z
    //   517: aload 12
    //   519: ifnull +10 -> 529
    //   522: aload 12
    //   524: invokeinterface 63 1 0
    //   529: iload 4
    //   531: istore_1
    //   532: aload_2
    //   533: ifnull +10 -> 543
    //   536: aload_2
    //   537: invokevirtual 103	android/database/sqlite/SQLiteDatabase:close	()V
    //   540: iload 4
    //   542: istore_1
    //   543: iload_3
    //   544: iconst_1
    //   545: iadd
    //   546: istore_3
    //   547: iload_1
    //   548: istore 4
    //   550: goto -504 -> 46
    //   553: astore 12
    //   555: aload 11
    //   557: astore_2
    //   558: aload 9
    //   560: astore 10
    //   562: aload 12
    //   564: astore 9
    //   566: aload 10
    //   568: ifnull +10 -> 578
    //   571: aload 10
    //   573: invokeinterface 63 1 0
    //   578: aload_2
    //   579: ifnull +7 -> 586
    //   582: aload_2
    //   583: invokevirtual 103	android/database/sqlite/SQLiteDatabase:close	()V
    //   586: aload 9
    //   588: athrow
    //   589: aload_0
    //   590: invokevirtual 118	com/google/android/gms/measurement/internal/zzgo:zzq	()Lcom/google/android/gms/measurement/internal/zzer;
    //   593: invokevirtual 180	com/google/android/gms/measurement/internal/zzer:zzw	()Lcom/google/android/gms/measurement/internal/zzet;
    //   596: ldc -74
    //   598: invokevirtual 131	com/google/android/gms/measurement/internal/zzet:zza	(Ljava/lang/String;)V
    //   601: iconst_0
    //   602: ireturn
    //   603: astore_2
    //   604: goto -183 -> 421
    //   607: astore 9
    //   609: aload 13
    //   611: astore 10
    //   613: goto -186 -> 427
    //   616: astore 9
    //   618: goto -300 -> 318
    // Local variable table:
    //   start	length	slot	name	signature
    //   0	621	0	this	zzen
    //   0	621	1	paramInt	int
    //   0	621	2	paramArrayOfByte	byte[]
    //   42	505	3	i	int
    //   44	505	4	j	int
    //   129	311	5	l1	long
    //   109	161	7	l2	long
    //   64	50	9	localObject1	Object
    //   163	1	9	localObject2	Object
    //   168	1	9	localSQLiteException1	SQLiteException
    //   173	7	9	localSQLiteFullException1	android.database.sqlite.SQLiteFullException
    //   321	1	9	localSQLiteException2	SQLiteException
    //   334	13	9	localObject3	Object
    //   351	27	9	localObject4	Object
    //   416	1	9	localObject5	Object
    //   434	153	9	localObject6	Object
    //   607	1	9	localSQLiteDatabaseLockedException1	android.database.sqlite.SQLiteDatabaseLockedException
    //   616	1	9	localSQLiteDatabaseLockedException2	android.database.sqlite.SQLiteDatabaseLockedException
    //   61	264	10	localObject7	Object
    //   329	1	10	localSQLiteFullException2	android.database.sqlite.SQLiteFullException
    //   344	113	10	localObject8	Object
    //   480	21	10	localSQLiteFullException3	android.database.sqlite.SQLiteFullException
    //   560	52	10	localObject9	Object
    //   80	37	11	arrayOfByte1	byte[]
    //   341	9	11	localSQLiteException3	SQLiteException
    //   437	119	11	arrayOfByte2	byte[]
    //   55	468	12	localObject10	Object
    //   553	10	12	localObject11	Object
    //   52	558	13	localObject12	Object
    //   58	54	14	localObject13	Object
    //   20	263	15	localContentValues	android.content.ContentValues
    // Exception table:
    //   from	to	target	type
    //   140	160	163	finally
    //   195	207	163	finally
    //   217	240	163	finally
    //   248	278	163	finally
    //   278	296	163	finally
    //   140	160	168	android/database/sqlite/SQLiteException
    //   195	207	168	android/database/sqlite/SQLiteException
    //   217	240	168	android/database/sqlite/SQLiteException
    //   248	278	168	android/database/sqlite/SQLiteException
    //   278	296	168	android/database/sqlite/SQLiteException
    //   140	160	173	android/database/sqlite/SQLiteFullException
    //   195	207	173	android/database/sqlite/SQLiteFullException
    //   217	240	173	android/database/sqlite/SQLiteFullException
    //   248	278	173	android/database/sqlite/SQLiteFullException
    //   278	296	173	android/database/sqlite/SQLiteFullException
    //   82	87	321	android/database/sqlite/SQLiteException
    //   104	108	321	android/database/sqlite/SQLiteException
    //   118	127	321	android/database/sqlite/SQLiteException
    //   82	87	329	android/database/sqlite/SQLiteFullException
    //   104	108	329	android/database/sqlite/SQLiteFullException
    //   118	127	329	android/database/sqlite/SQLiteFullException
    //   66	71	334	finally
    //   66	71	341	android/database/sqlite/SQLiteException
    //   357	368	416	finally
    //   368	387	416	finally
    //   66	71	480	android/database/sqlite/SQLiteFullException
    //   82	87	553	finally
    //   104	108	553	finally
    //   118	127	553	finally
    //   439	444	553	finally
    //   491	505	553	finally
    //   512	517	553	finally
    //   66	71	603	android/database/sqlite/SQLiteDatabaseLockedException
    //   82	87	607	android/database/sqlite/SQLiteDatabaseLockedException
    //   104	108	607	android/database/sqlite/SQLiteDatabaseLockedException
    //   118	127	607	android/database/sqlite/SQLiteDatabaseLockedException
    //   140	160	616	android/database/sqlite/SQLiteDatabaseLockedException
    //   195	207	616	android/database/sqlite/SQLiteDatabaseLockedException
    //   217	240	616	android/database/sqlite/SQLiteDatabaseLockedException
    //   248	278	616	android/database/sqlite/SQLiteDatabaseLockedException
    //   278	296	616	android/database/sqlite/SQLiteDatabaseLockedException
  }
  
  private final SQLiteDatabase zzad()
    throws SQLiteException
  {
    if (this.zzb) {
      return null;
    }
    SQLiteDatabase localSQLiteDatabase = this.zza.getWritableDatabase();
    if (localSQLiteDatabase == null)
    {
      this.zzb = true;
      return null;
    }
    return localSQLiteDatabase;
  }
  
  private final boolean zzae()
  {
    return zzm().getDatabasePath("google_app_measurement_local.db").exists();
  }
  
  /* Error */
  public final java.util.List<com.google.android.gms.common.internal.safeparcel.AbstractSafeParcelable> zza(int paramInt)
  {
    // Byte code:
    //   0: aload_0
    //   1: invokevirtual 75	com/google/android/gms/measurement/internal/zzgo:zzc	()V
    //   4: aload_0
    //   5: getfield 77	com/google/android/gms/measurement/internal/zzen:zzb	Z
    //   8: istore 4
    //   10: aconst_null
    //   11: astore 14
    //   13: aconst_null
    //   14: astore 15
    //   16: iload 4
    //   18: ifeq +5 -> 23
    //   21: aconst_null
    //   22: areturn
    //   23: new 203	java/util/ArrayList
    //   26: dup
    //   27: invokespecial 204	java/util/ArrayList:<init>	()V
    //   30: astore 16
    //   32: aload_0
    //   33: invokespecial 206	com/google/android/gms/measurement/internal/zzen:zzae	()Z
    //   36: ifne +6 -> 42
    //   39: aload 16
    //   41: areturn
    //   42: iconst_0
    //   43: istore_1
    //   44: iconst_5
    //   45: istore_2
    //   46: iload_1
    //   47: iconst_5
    //   48: if_icmpge +1062 -> 1110
    //   51: aload_0
    //   52: invokespecial 102	com/google/android/gms/measurement/internal/zzen:zzad	()Landroid/database/sqlite/SQLiteDatabase;
    //   55: astore 11
    //   57: aload 11
    //   59: astore 9
    //   61: aload 9
    //   63: ifnonnull +30 -> 93
    //   66: aload_0
    //   67: iconst_1
    //   68: putfield 77	com/google/android/gms/measurement/internal/zzen:zzb	Z
    //   71: aload 9
    //   73: ifnull +8 -> 81
    //   76: aload 9
    //   78: invokevirtual 103	android/database/sqlite/SQLiteDatabase:close	()V
    //   81: aconst_null
    //   82: areturn
    //   83: astore 13
    //   85: goto +688 -> 773
    //   88: astore 13
    //   90: goto +709 -> 799
    //   93: aload 9
    //   95: invokevirtual 106	android/database/sqlite/SQLiteDatabase:beginTransaction	()V
    //   98: aload 9
    //   100: invokestatic 208	com/google/android/gms/measurement/internal/zzen:zza	(Landroid/database/sqlite/SQLiteDatabase;)J
    //   103: lstore 7
    //   105: ldc2_w 64
    //   108: lstore 5
    //   110: lload 7
    //   112: ldc2_w 64
    //   115: lcmp
    //   116: ifeq +24 -> 140
    //   119: ldc -46
    //   121: astore 12
    //   123: iconst_1
    //   124: anewarray 33	java/lang/String
    //   127: dup
    //   128: iconst_0
    //   129: lload 7
    //   131: invokestatic 212	java/lang/String:valueOf	(J)Ljava/lang/String;
    //   134: aastore
    //   135: astore 13
    //   137: goto +10 -> 147
    //   140: aconst_null
    //   141: astore 12
    //   143: aload 12
    //   145: astore 13
    //   147: bipush 100
    //   149: invokestatic 215	java/lang/Integer:toString	(I)Ljava/lang/String;
    //   152: astore 17
    //   154: aload 9
    //   156: astore 10
    //   158: aload 9
    //   160: ldc 31
    //   162: iconst_3
    //   163: anewarray 33	java/lang/String
    //   166: dup
    //   167: iconst_0
    //   168: ldc 35
    //   170: aastore
    //   171: dup
    //   172: iconst_1
    //   173: ldc 83
    //   175: aastore
    //   176: dup
    //   177: iconst_2
    //   178: ldc 95
    //   180: aastore
    //   181: aload 12
    //   183: aload 13
    //   185: aconst_null
    //   186: aconst_null
    //   187: ldc -39
    //   189: aload 17
    //   191: invokevirtual 49	android/database/sqlite/SQLiteDatabase:query	(Ljava/lang/String;[Ljava/lang/String;Ljava/lang/String;[Ljava/lang/String;Ljava/lang/String;Ljava/lang/String;Ljava/lang/String;Ljava/lang/String;)Landroid/database/Cursor;
    //   194: astore 9
    //   196: aload 9
    //   198: invokeinterface 220 1 0
    //   203: ifeq +407 -> 610
    //   206: aload 9
    //   208: iconst_0
    //   209: invokeinterface 59 2 0
    //   214: lstore 7
    //   216: aload 9
    //   218: iconst_1
    //   219: invokeinterface 224 2 0
    //   224: istore_3
    //   225: aload 9
    //   227: iconst_2
    //   228: invokeinterface 228 2 0
    //   233: astore 17
    //   235: iload_3
    //   236: ifne +109 -> 345
    //   239: invokestatic 234	android/os/Parcel:obtain	()Landroid/os/Parcel;
    //   242: astore 12
    //   244: aload 12
    //   246: aload 17
    //   248: iconst_0
    //   249: aload 17
    //   251: arraylength
    //   252: invokevirtual 238	android/os/Parcel:unmarshall	([BII)V
    //   255: aload 12
    //   257: iconst_0
    //   258: invokevirtual 242	android/os/Parcel:setDataPosition	(I)V
    //   261: getstatic 248	com/google/android/gms/measurement/internal/zzar:CREATOR	Landroid/os/Parcelable$Creator;
    //   264: aload 12
    //   266: invokeinterface 254 2 0
    //   271: checkcast 244	com/google/android/gms/measurement/internal/zzar
    //   274: astore 13
    //   276: aload 12
    //   278: invokevirtual 257	android/os/Parcel:recycle	()V
    //   281: lload 7
    //   283: lstore 5
    //   285: aload 13
    //   287: ifnull -91 -> 196
    //   290: aload 16
    //   292: aload 13
    //   294: invokeinterface 263 2 0
    //   299: pop
    //   300: lload 7
    //   302: lstore 5
    //   304: goto -108 -> 196
    //   307: astore 13
    //   309: goto +28 -> 337
    //   312: aload_0
    //   313: invokevirtual 118	com/google/android/gms/measurement/internal/zzgo:zzq	()Lcom/google/android/gms/measurement/internal/zzer;
    //   316: invokevirtual 124	com/google/android/gms/measurement/internal/zzer:zze	()Lcom/google/android/gms/measurement/internal/zzet;
    //   319: ldc_w 265
    //   322: invokevirtual 131	com/google/android/gms/measurement/internal/zzet:zza	(Ljava/lang/String;)V
    //   325: aload 12
    //   327: invokevirtual 257	android/os/Parcel:recycle	()V
    //   330: lload 7
    //   332: lstore 5
    //   334: goto -138 -> 196
    //   337: aload 12
    //   339: invokevirtual 257	android/os/Parcel:recycle	()V
    //   342: aload 13
    //   344: athrow
    //   345: iload_3
    //   346: iconst_1
    //   347: if_icmpne +108 -> 455
    //   350: invokestatic 234	android/os/Parcel:obtain	()Landroid/os/Parcel;
    //   353: astore 13
    //   355: aload 13
    //   357: aload 17
    //   359: iconst_0
    //   360: aload 17
    //   362: arraylength
    //   363: invokevirtual 238	android/os/Parcel:unmarshall	([BII)V
    //   366: aload 13
    //   368: iconst_0
    //   369: invokevirtual 242	android/os/Parcel:setDataPosition	(I)V
    //   372: getstatic 268	com/google/android/gms/measurement/internal/zzkr:CREATOR	Landroid/os/Parcelable$Creator;
    //   375: aload 13
    //   377: invokeinterface 254 2 0
    //   382: checkcast 267	com/google/android/gms/measurement/internal/zzkr
    //   385: astore 12
    //   387: aload 13
    //   389: invokevirtual 257	android/os/Parcel:recycle	()V
    //   392: goto +29 -> 421
    //   395: astore 12
    //   397: goto +50 -> 447
    //   400: aload_0
    //   401: invokevirtual 118	com/google/android/gms/measurement/internal/zzgo:zzq	()Lcom/google/android/gms/measurement/internal/zzer;
    //   404: invokevirtual 124	com/google/android/gms/measurement/internal/zzer:zze	()Lcom/google/android/gms/measurement/internal/zzet;
    //   407: ldc_w 270
    //   410: invokevirtual 131	com/google/android/gms/measurement/internal/zzet:zza	(Ljava/lang/String;)V
    //   413: aload 13
    //   415: invokevirtual 257	android/os/Parcel:recycle	()V
    //   418: aconst_null
    //   419: astore 12
    //   421: lload 7
    //   423: lstore 5
    //   425: aload 12
    //   427: ifnull -231 -> 196
    //   430: aload 16
    //   432: aload 12
    //   434: invokeinterface 263 2 0
    //   439: pop
    //   440: lload 7
    //   442: lstore 5
    //   444: goto -248 -> 196
    //   447: aload 13
    //   449: invokevirtual 257	android/os/Parcel:recycle	()V
    //   452: aload 12
    //   454: athrow
    //   455: iload_3
    //   456: iconst_2
    //   457: if_icmpne +108 -> 565
    //   460: invokestatic 234	android/os/Parcel:obtain	()Landroid/os/Parcel;
    //   463: astore 13
    //   465: aload 13
    //   467: aload 17
    //   469: iconst_0
    //   470: aload 17
    //   472: arraylength
    //   473: invokevirtual 238	android/os/Parcel:unmarshall	([BII)V
    //   476: aload 13
    //   478: iconst_0
    //   479: invokevirtual 242	android/os/Parcel:setDataPosition	(I)V
    //   482: getstatic 273	com/google/android/gms/measurement/internal/zzw:CREATOR	Landroid/os/Parcelable$Creator;
    //   485: aload 13
    //   487: invokeinterface 254 2 0
    //   492: checkcast 272	com/google/android/gms/measurement/internal/zzw
    //   495: astore 12
    //   497: aload 13
    //   499: invokevirtual 257	android/os/Parcel:recycle	()V
    //   502: goto +29 -> 531
    //   505: astore 12
    //   507: goto +50 -> 557
    //   510: aload_0
    //   511: invokevirtual 118	com/google/android/gms/measurement/internal/zzgo:zzq	()Lcom/google/android/gms/measurement/internal/zzer;
    //   514: invokevirtual 124	com/google/android/gms/measurement/internal/zzer:zze	()Lcom/google/android/gms/measurement/internal/zzet;
    //   517: ldc_w 275
    //   520: invokevirtual 131	com/google/android/gms/measurement/internal/zzet:zza	(Ljava/lang/String;)V
    //   523: aload 13
    //   525: invokevirtual 257	android/os/Parcel:recycle	()V
    //   528: aconst_null
    //   529: astore 12
    //   531: lload 7
    //   533: lstore 5
    //   535: aload 12
    //   537: ifnull -341 -> 196
    //   540: aload 16
    //   542: aload 12
    //   544: invokeinterface 263 2 0
    //   549: pop
    //   550: lload 7
    //   552: lstore 5
    //   554: goto -358 -> 196
    //   557: aload 13
    //   559: invokevirtual 257	android/os/Parcel:recycle	()V
    //   562: aload 12
    //   564: athrow
    //   565: iload_3
    //   566: iconst_3
    //   567: if_icmpne +23 -> 590
    //   570: aload_0
    //   571: invokevirtual 118	com/google/android/gms/measurement/internal/zzgo:zzq	()Lcom/google/android/gms/measurement/internal/zzer;
    //   574: invokevirtual 278	com/google/android/gms/measurement/internal/zzer:zzh	()Lcom/google/android/gms/measurement/internal/zzet;
    //   577: ldc_w 280
    //   580: invokevirtual 131	com/google/android/gms/measurement/internal/zzet:zza	(Ljava/lang/String;)V
    //   583: lload 7
    //   585: lstore 5
    //   587: goto -391 -> 196
    //   590: aload_0
    //   591: invokevirtual 118	com/google/android/gms/measurement/internal/zzgo:zzq	()Lcom/google/android/gms/measurement/internal/zzer;
    //   594: invokevirtual 124	com/google/android/gms/measurement/internal/zzer:zze	()Lcom/google/android/gms/measurement/internal/zzet;
    //   597: ldc_w 282
    //   600: invokevirtual 131	com/google/android/gms/measurement/internal/zzet:zza	(Ljava/lang/String;)V
    //   603: lload 7
    //   605: lstore 5
    //   607: goto -411 -> 196
    //   610: aload 10
    //   612: ldc 31
    //   614: ldc_w 284
    //   617: iconst_1
    //   618: anewarray 33	java/lang/String
    //   621: dup
    //   622: iconst_0
    //   623: lload 5
    //   625: invokestatic 139	java/lang/Long:toString	(J)Ljava/lang/String;
    //   628: aastore
    //   629: invokevirtual 143	android/database/sqlite/SQLiteDatabase:delete	(Ljava/lang/String;Ljava/lang/String;[Ljava/lang/String;)I
    //   632: aload 16
    //   634: invokeinterface 288 1 0
    //   639: if_icmpge +16 -> 655
    //   642: aload_0
    //   643: invokevirtual 118	com/google/android/gms/measurement/internal/zzgo:zzq	()Lcom/google/android/gms/measurement/internal/zzer;
    //   646: invokevirtual 124	com/google/android/gms/measurement/internal/zzer:zze	()Lcom/google/android/gms/measurement/internal/zzet;
    //   649: ldc_w 290
    //   652: invokevirtual 131	com/google/android/gms/measurement/internal/zzet:zza	(Ljava/lang/String;)V
    //   655: aload 10
    //   657: invokevirtual 158	android/database/sqlite/SQLiteDatabase:setTransactionSuccessful	()V
    //   660: aload 10
    //   662: invokevirtual 161	android/database/sqlite/SQLiteDatabase:endTransaction	()V
    //   665: aload 9
    //   667: ifnull +10 -> 677
    //   670: aload 9
    //   672: invokeinterface 63 1 0
    //   677: aload 10
    //   679: ifnull +8 -> 687
    //   682: aload 10
    //   684: invokevirtual 103	android/database/sqlite/SQLiteDatabase:close	()V
    //   687: aload 16
    //   689: areturn
    //   690: astore 12
    //   692: aload 9
    //   694: astore 11
    //   696: aload 12
    //   698: astore 9
    //   700: aload 10
    //   702: astore 12
    //   704: goto +381 -> 1085
    //   707: astore 13
    //   709: goto +26 -> 735
    //   712: astore 13
    //   714: goto +37 -> 751
    //   717: astore 9
    //   719: aload 14
    //   721: astore 11
    //   723: aload 10
    //   725: astore 12
    //   727: goto +358 -> 1085
    //   730: astore 13
    //   732: aconst_null
    //   733: astore 9
    //   735: aload 9
    //   737: astore 11
    //   739: aload 10
    //   741: astore 12
    //   743: goto +87 -> 830
    //   746: astore 13
    //   748: aconst_null
    //   749: astore 9
    //   751: aload 9
    //   753: astore 11
    //   755: aload 10
    //   757: astore 12
    //   759: goto +237 -> 996
    //   762: astore 10
    //   764: aload 15
    //   766: astore 11
    //   768: goto +309 -> 1077
    //   771: astore 13
    //   773: aconst_null
    //   774: astore 11
    //   776: aload 9
    //   778: astore 12
    //   780: goto +50 -> 830
    //   783: aconst_null
    //   784: astore 9
    //   786: aload 11
    //   788: astore 12
    //   790: aload 9
    //   792: astore 11
    //   794: goto +142 -> 936
    //   797: astore 13
    //   799: aconst_null
    //   800: astore 11
    //   802: aload 9
    //   804: astore 12
    //   806: goto +190 -> 996
    //   809: astore 9
    //   811: aconst_null
    //   812: astore 12
    //   814: aload 14
    //   816: astore 11
    //   818: goto +267 -> 1085
    //   821: astore 13
    //   823: aconst_null
    //   824: astore 11
    //   826: aload 11
    //   828: astore 12
    //   830: aload 12
    //   832: ifnull +32 -> 864
    //   835: aload 11
    //   837: astore 10
    //   839: aload 12
    //   841: astore 9
    //   843: aload 12
    //   845: invokevirtual 164	android/database/sqlite/SQLiteDatabase:inTransaction	()Z
    //   848: ifeq +16 -> 864
    //   851: aload 11
    //   853: astore 10
    //   855: aload 12
    //   857: astore 9
    //   859: aload 12
    //   861: invokevirtual 161	android/database/sqlite/SQLiteDatabase:endTransaction	()V
    //   864: aload 11
    //   866: astore 10
    //   868: aload 12
    //   870: astore 9
    //   872: aload_0
    //   873: invokevirtual 118	com/google/android/gms/measurement/internal/zzgo:zzq	()Lcom/google/android/gms/measurement/internal/zzer;
    //   876: invokevirtual 124	com/google/android/gms/measurement/internal/zzer:zze	()Lcom/google/android/gms/measurement/internal/zzet;
    //   879: ldc_w 292
    //   882: aload 13
    //   884: invokevirtual 169	com/google/android/gms/measurement/internal/zzet:zza	(Ljava/lang/String;Ljava/lang/Object;)V
    //   887: aload 11
    //   889: astore 10
    //   891: aload 12
    //   893: astore 9
    //   895: aload_0
    //   896: iconst_1
    //   897: putfield 77	com/google/android/gms/measurement/internal/zzen:zzb	Z
    //   900: aload 11
    //   902: ifnull +10 -> 912
    //   905: aload 11
    //   907: invokeinterface 63 1 0
    //   912: iload_2
    //   913: istore_3
    //   914: aload 12
    //   916: ifnull +142 -> 1058
    //   919: aload 12
    //   921: invokevirtual 103	android/database/sqlite/SQLiteDatabase:close	()V
    //   924: iload_2
    //   925: istore_3
    //   926: goto +132 -> 1058
    //   929: aconst_null
    //   930: astore 11
    //   932: aload 11
    //   934: astore 12
    //   936: iload_2
    //   937: i2l
    //   938: lstore 5
    //   940: aload 11
    //   942: astore 10
    //   944: aload 12
    //   946: astore 9
    //   948: lload 5
    //   950: invokestatic 175	android/os/SystemClock:sleep	(J)V
    //   953: iload_2
    //   954: bipush 20
    //   956: iadd
    //   957: istore_2
    //   958: aload 11
    //   960: ifnull +10 -> 970
    //   963: aload 11
    //   965: invokeinterface 63 1 0
    //   970: iload_2
    //   971: istore_3
    //   972: aload 12
    //   974: ifnull +84 -> 1058
    //   977: aload 12
    //   979: invokevirtual 103	android/database/sqlite/SQLiteDatabase:close	()V
    //   982: iload_2
    //   983: istore_3
    //   984: goto +74 -> 1058
    //   987: astore 13
    //   989: aconst_null
    //   990: astore 11
    //   992: aload 11
    //   994: astore 12
    //   996: aload 11
    //   998: astore 10
    //   1000: aload 12
    //   1002: astore 9
    //   1004: aload_0
    //   1005: invokevirtual 118	com/google/android/gms/measurement/internal/zzgo:zzq	()Lcom/google/android/gms/measurement/internal/zzer;
    //   1008: invokevirtual 124	com/google/android/gms/measurement/internal/zzer:zze	()Lcom/google/android/gms/measurement/internal/zzet;
    //   1011: ldc_w 292
    //   1014: aload 13
    //   1016: invokevirtual 169	com/google/android/gms/measurement/internal/zzet:zza	(Ljava/lang/String;Ljava/lang/Object;)V
    //   1019: aload 11
    //   1021: astore 10
    //   1023: aload 12
    //   1025: astore 9
    //   1027: aload_0
    //   1028: iconst_1
    //   1029: putfield 77	com/google/android/gms/measurement/internal/zzen:zzb	Z
    //   1032: aload 11
    //   1034: ifnull +10 -> 1044
    //   1037: aload 11
    //   1039: invokeinterface 63 1 0
    //   1044: iload_2
    //   1045: istore_3
    //   1046: aload 12
    //   1048: ifnull +10 -> 1058
    //   1051: aload 12
    //   1053: invokevirtual 103	android/database/sqlite/SQLiteDatabase:close	()V
    //   1056: iload_2
    //   1057: istore_3
    //   1058: iload_1
    //   1059: iconst_1
    //   1060: iadd
    //   1061: istore_1
    //   1062: iload_3
    //   1063: istore_2
    //   1064: goto -1018 -> 46
    //   1067: astore 12
    //   1069: aload 10
    //   1071: astore 11
    //   1073: aload 12
    //   1075: astore 10
    //   1077: aload 9
    //   1079: astore 12
    //   1081: aload 10
    //   1083: astore 9
    //   1085: aload 11
    //   1087: ifnull +10 -> 1097
    //   1090: aload 11
    //   1092: invokeinterface 63 1 0
    //   1097: aload 12
    //   1099: ifnull +8 -> 1107
    //   1102: aload 12
    //   1104: invokevirtual 103	android/database/sqlite/SQLiteDatabase:close	()V
    //   1107: aload 9
    //   1109: athrow
    //   1110: aload_0
    //   1111: invokevirtual 118	com/google/android/gms/measurement/internal/zzgo:zzq	()Lcom/google/android/gms/measurement/internal/zzer;
    //   1114: invokevirtual 278	com/google/android/gms/measurement/internal/zzer:zzh	()Lcom/google/android/gms/measurement/internal/zzet;
    //   1117: ldc_w 294
    //   1120: invokevirtual 131	com/google/android/gms/measurement/internal/zzet:zza	(Ljava/lang/String;)V
    //   1123: aconst_null
    //   1124: areturn
    //   1125: astore 9
    //   1127: goto -198 -> 929
    //   1130: astore 9
    //   1132: goto -349 -> 783
    //   1135: astore 9
    //   1137: goto -354 -> 783
    //   1140: astore 10
    //   1142: goto -356 -> 786
    //   1145: astore 13
    //   1147: goto -835 -> 312
    //   1150: astore 12
    //   1152: goto -752 -> 400
    //   1155: astore 12
    //   1157: goto -647 -> 510
    // Local variable table:
    //   start	length	slot	name	signature
    //   0	1160	0	this	zzen
    //   0	1160	1	paramInt	int
    //   45	1019	2	i	int
    //   224	839	3	j	int
    //   8	9	4	bool	boolean
    //   108	841	5	l1	long
    //   103	501	7	l2	long
    //   59	640	9	localObject1	Object
    //   717	1	9	localObject2	Object
    //   733	70	9	localObject3	Object
    //   809	1	9	localObject4	Object
    //   841	267	9	localObject5	Object
    //   1125	1	9	localSQLiteDatabaseLockedException1	android.database.sqlite.SQLiteDatabaseLockedException
    //   1130	1	9	localSQLiteDatabaseLockedException2	android.database.sqlite.SQLiteDatabaseLockedException
    //   1135	1	9	localSQLiteDatabaseLockedException3	android.database.sqlite.SQLiteDatabaseLockedException
    //   156	600	10	localObject6	Object
    //   762	1	10	localObject7	Object
    //   837	245	10	localObject8	Object
    //   1140	1	10	localSQLiteDatabaseLockedException4	android.database.sqlite.SQLiteDatabaseLockedException
    //   55	1036	11	localObject9	Object
    //   121	265	12	localObject10	Object
    //   395	1	12	localObject11	Object
    //   419	77	12	localObject12	Object
    //   505	1	12	localObject13	Object
    //   529	34	12	localObject14	Object
    //   690	7	12	localObject15	Object
    //   702	350	12	localObject16	Object
    //   1067	7	12	localObject17	Object
    //   1079	24	12	localObject18	Object
    //   1150	1	12	localParseException1	com.google.android.gms.common.internal.safeparcel.SafeParcelReader.ParseException
    //   1155	1	12	localParseException2	com.google.android.gms.common.internal.safeparcel.SafeParcelReader.ParseException
    //   83	1	13	localSQLiteException1	SQLiteException
    //   88	1	13	localSQLiteFullException1	android.database.sqlite.SQLiteFullException
    //   135	158	13	localObject19	Object
    //   307	36	13	localObject20	Object
    //   353	205	13	localParcel	Parcel
    //   707	1	13	localSQLiteException2	SQLiteException
    //   712	1	13	localSQLiteFullException2	android.database.sqlite.SQLiteFullException
    //   730	1	13	localSQLiteException3	SQLiteException
    //   746	1	13	localSQLiteFullException3	android.database.sqlite.SQLiteFullException
    //   771	1	13	localSQLiteException4	SQLiteException
    //   797	1	13	localSQLiteFullException4	android.database.sqlite.SQLiteFullException
    //   821	62	13	localSQLiteException5	SQLiteException
    //   987	28	13	localSQLiteFullException5	android.database.sqlite.SQLiteFullException
    //   1145	1	13	localParseException3	com.google.android.gms.common.internal.safeparcel.SafeParcelReader.ParseException
    //   11	804	14	localObject21	Object
    //   14	751	15	localObject22	Object
    //   30	658	16	localArrayList	java.util.ArrayList
    //   152	319	17	localObject23	Object
    // Exception table:
    //   from	to	target	type
    //   66	71	83	android/database/sqlite/SQLiteException
    //   66	71	88	android/database/sqlite/SQLiteFullException
    //   244	276	307	finally
    //   312	325	307	finally
    //   355	387	395	finally
    //   400	413	395	finally
    //   465	497	505	finally
    //   510	523	505	finally
    //   196	235	690	finally
    //   239	244	690	finally
    //   276	281	690	finally
    //   290	300	690	finally
    //   325	330	690	finally
    //   337	345	690	finally
    //   350	355	690	finally
    //   387	392	690	finally
    //   413	418	690	finally
    //   430	440	690	finally
    //   447	455	690	finally
    //   460	465	690	finally
    //   497	502	690	finally
    //   523	528	690	finally
    //   540	550	690	finally
    //   557	565	690	finally
    //   570	583	690	finally
    //   590	603	690	finally
    //   610	655	690	finally
    //   655	665	690	finally
    //   196	235	707	android/database/sqlite/SQLiteException
    //   239	244	707	android/database/sqlite/SQLiteException
    //   276	281	707	android/database/sqlite/SQLiteException
    //   290	300	707	android/database/sqlite/SQLiteException
    //   325	330	707	android/database/sqlite/SQLiteException
    //   337	345	707	android/database/sqlite/SQLiteException
    //   350	355	707	android/database/sqlite/SQLiteException
    //   387	392	707	android/database/sqlite/SQLiteException
    //   413	418	707	android/database/sqlite/SQLiteException
    //   430	440	707	android/database/sqlite/SQLiteException
    //   447	455	707	android/database/sqlite/SQLiteException
    //   460	465	707	android/database/sqlite/SQLiteException
    //   497	502	707	android/database/sqlite/SQLiteException
    //   523	528	707	android/database/sqlite/SQLiteException
    //   540	550	707	android/database/sqlite/SQLiteException
    //   557	565	707	android/database/sqlite/SQLiteException
    //   570	583	707	android/database/sqlite/SQLiteException
    //   590	603	707	android/database/sqlite/SQLiteException
    //   610	655	707	android/database/sqlite/SQLiteException
    //   655	665	707	android/database/sqlite/SQLiteException
    //   196	235	712	android/database/sqlite/SQLiteFullException
    //   239	244	712	android/database/sqlite/SQLiteFullException
    //   276	281	712	android/database/sqlite/SQLiteFullException
    //   290	300	712	android/database/sqlite/SQLiteFullException
    //   325	330	712	android/database/sqlite/SQLiteFullException
    //   337	345	712	android/database/sqlite/SQLiteFullException
    //   350	355	712	android/database/sqlite/SQLiteFullException
    //   387	392	712	android/database/sqlite/SQLiteFullException
    //   413	418	712	android/database/sqlite/SQLiteFullException
    //   430	440	712	android/database/sqlite/SQLiteFullException
    //   447	455	712	android/database/sqlite/SQLiteFullException
    //   460	465	712	android/database/sqlite/SQLiteFullException
    //   497	502	712	android/database/sqlite/SQLiteFullException
    //   523	528	712	android/database/sqlite/SQLiteFullException
    //   540	550	712	android/database/sqlite/SQLiteFullException
    //   557	565	712	android/database/sqlite/SQLiteFullException
    //   570	583	712	android/database/sqlite/SQLiteFullException
    //   590	603	712	android/database/sqlite/SQLiteFullException
    //   610	655	712	android/database/sqlite/SQLiteFullException
    //   655	665	712	android/database/sqlite/SQLiteFullException
    //   158	196	717	finally
    //   158	196	730	android/database/sqlite/SQLiteException
    //   158	196	746	android/database/sqlite/SQLiteFullException
    //   66	71	762	finally
    //   93	105	762	finally
    //   147	154	762	finally
    //   93	105	771	android/database/sqlite/SQLiteException
    //   147	154	771	android/database/sqlite/SQLiteException
    //   93	105	797	android/database/sqlite/SQLiteFullException
    //   147	154	797	android/database/sqlite/SQLiteFullException
    //   51	57	809	finally
    //   51	57	821	android/database/sqlite/SQLiteException
    //   51	57	987	android/database/sqlite/SQLiteFullException
    //   843	851	1067	finally
    //   859	864	1067	finally
    //   872	887	1067	finally
    //   895	900	1067	finally
    //   948	953	1067	finally
    //   1004	1019	1067	finally
    //   1027	1032	1067	finally
    //   51	57	1125	android/database/sqlite/SQLiteDatabaseLockedException
    //   66	71	1130	android/database/sqlite/SQLiteDatabaseLockedException
    //   93	105	1130	android/database/sqlite/SQLiteDatabaseLockedException
    //   147	154	1130	android/database/sqlite/SQLiteDatabaseLockedException
    //   158	196	1135	android/database/sqlite/SQLiteDatabaseLockedException
    //   196	235	1140	android/database/sqlite/SQLiteDatabaseLockedException
    //   239	244	1140	android/database/sqlite/SQLiteDatabaseLockedException
    //   276	281	1140	android/database/sqlite/SQLiteDatabaseLockedException
    //   290	300	1140	android/database/sqlite/SQLiteDatabaseLockedException
    //   325	330	1140	android/database/sqlite/SQLiteDatabaseLockedException
    //   337	345	1140	android/database/sqlite/SQLiteDatabaseLockedException
    //   350	355	1140	android/database/sqlite/SQLiteDatabaseLockedException
    //   387	392	1140	android/database/sqlite/SQLiteDatabaseLockedException
    //   413	418	1140	android/database/sqlite/SQLiteDatabaseLockedException
    //   430	440	1140	android/database/sqlite/SQLiteDatabaseLockedException
    //   447	455	1140	android/database/sqlite/SQLiteDatabaseLockedException
    //   460	465	1140	android/database/sqlite/SQLiteDatabaseLockedException
    //   497	502	1140	android/database/sqlite/SQLiteDatabaseLockedException
    //   523	528	1140	android/database/sqlite/SQLiteDatabaseLockedException
    //   540	550	1140	android/database/sqlite/SQLiteDatabaseLockedException
    //   557	565	1140	android/database/sqlite/SQLiteDatabaseLockedException
    //   570	583	1140	android/database/sqlite/SQLiteDatabaseLockedException
    //   590	603	1140	android/database/sqlite/SQLiteDatabaseLockedException
    //   610	655	1140	android/database/sqlite/SQLiteDatabaseLockedException
    //   655	665	1140	android/database/sqlite/SQLiteDatabaseLockedException
    //   244	276	1145	com/google/android/gms/common/internal/safeparcel/SafeParcelReader$ParseException
    //   355	387	1150	com/google/android/gms/common/internal/safeparcel/SafeParcelReader$ParseException
    //   465	497	1155	com/google/android/gms/common/internal/safeparcel/SafeParcelReader$ParseException
  }
  
  public final boolean zza(zzar paramzzar)
  {
    Parcel localParcel = Parcel.obtain();
    paramzzar.writeToParcel(localParcel, 0);
    paramzzar = localParcel.marshall();
    localParcel.recycle();
    if (paramzzar.length > 131072)
    {
      zzq().zzf().zza("Event is too long for local database. Sending event directly to service");
      return false;
    }
    return zza(0, paramzzar);
  }
  
  public final boolean zza(zzkr paramzzkr)
  {
    Parcel localParcel = Parcel.obtain();
    paramzzkr.writeToParcel(localParcel, 0);
    paramzzkr = localParcel.marshall();
    localParcel.recycle();
    if (paramzzkr.length > 131072)
    {
      zzq().zzf().zza("User property too long for local database. Sending directly to service");
      return false;
    }
    return zza(1, paramzzkr);
  }
  
  public final boolean zza(zzw paramzzw)
  {
    zzo();
    paramzzw = zzkw.zza(paramzzw);
    if (paramzzw.length > 131072)
    {
      zzq().zzf().zza("Conditional user property too long for local database. Sending directly to service");
      return false;
    }
    return zza(2, paramzzw);
  }
  
  public final void zzaa()
  {
    zzc();
    try
    {
      int i = zzad().delete("messages", null, null) + 0;
      if (i > 0) {
        zzq().zzw().zza("Reset local analytics data. records", Integer.valueOf(i));
      }
      return;
    }
    catch (SQLiteException localSQLiteException)
    {
      zzq().zze().zza("Error resetting local analytics data. error", localSQLiteException);
    }
  }
  
  public final boolean zzab()
  {
    return zza(3, new byte[0]);
  }
  
  /* Error */
  public final boolean zzac()
  {
    // Byte code:
    //   0: aload_0
    //   1: invokevirtual 75	com/google/android/gms/measurement/internal/zzgo:zzc	()V
    //   4: aload_0
    //   5: getfield 77	com/google/android/gms/measurement/internal/zzen:zzb	Z
    //   8: ifeq +5 -> 13
    //   11: iconst_0
    //   12: ireturn
    //   13: aload_0
    //   14: invokespecial 206	com/google/android/gms/measurement/internal/zzen:zzae	()Z
    //   17: ifne +5 -> 22
    //   20: iconst_0
    //   21: ireturn
    //   22: iconst_0
    //   23: istore_2
    //   24: iconst_5
    //   25: istore_3
    //   26: iload_2
    //   27: iconst_5
    //   28: if_icmpge +351 -> 379
    //   31: aconst_null
    //   32: astore 8
    //   34: aconst_null
    //   35: astore 9
    //   37: aconst_null
    //   38: astore 10
    //   40: aconst_null
    //   41: astore 6
    //   43: aload_0
    //   44: invokespecial 102	com/google/android/gms/measurement/internal/zzen:zzad	()Landroid/database/sqlite/SQLiteDatabase;
    //   47: astore 7
    //   49: aload 7
    //   51: ifnonnull +36 -> 87
    //   54: aload 7
    //   56: astore 6
    //   58: aload 7
    //   60: astore 8
    //   62: aload 7
    //   64: astore 9
    //   66: aload 7
    //   68: astore 10
    //   70: aload_0
    //   71: iconst_1
    //   72: putfield 77	com/google/android/gms/measurement/internal/zzen:zzb	Z
    //   75: aload 7
    //   77: ifnull +8 -> 85
    //   80: aload 7
    //   82: invokevirtual 103	android/database/sqlite/SQLiteDatabase:close	()V
    //   85: iconst_0
    //   86: ireturn
    //   87: aload 7
    //   89: astore 6
    //   91: aload 7
    //   93: astore 8
    //   95: aload 7
    //   97: astore 9
    //   99: aload 7
    //   101: astore 10
    //   103: aload 7
    //   105: invokevirtual 106	android/database/sqlite/SQLiteDatabase:beginTransaction	()V
    //   108: aload 7
    //   110: astore 6
    //   112: aload 7
    //   114: astore 8
    //   116: aload 7
    //   118: astore 9
    //   120: aload 7
    //   122: astore 10
    //   124: aload 7
    //   126: ldc 31
    //   128: ldc_w 340
    //   131: iconst_1
    //   132: anewarray 33	java/lang/String
    //   135: dup
    //   136: iconst_0
    //   137: iconst_3
    //   138: invokestatic 215	java/lang/Integer:toString	(I)Ljava/lang/String;
    //   141: aastore
    //   142: invokevirtual 143	android/database/sqlite/SQLiteDatabase:delete	(Ljava/lang/String;Ljava/lang/String;[Ljava/lang/String;)I
    //   145: pop
    //   146: aload 7
    //   148: astore 6
    //   150: aload 7
    //   152: astore 8
    //   154: aload 7
    //   156: astore 9
    //   158: aload 7
    //   160: astore 10
    //   162: aload 7
    //   164: invokevirtual 158	android/database/sqlite/SQLiteDatabase:setTransactionSuccessful	()V
    //   167: aload 7
    //   169: astore 6
    //   171: aload 7
    //   173: astore 8
    //   175: aload 7
    //   177: astore 9
    //   179: aload 7
    //   181: astore 10
    //   183: aload 7
    //   185: invokevirtual 161	android/database/sqlite/SQLiteDatabase:endTransaction	()V
    //   188: aload 7
    //   190: ifnull +8 -> 198
    //   193: aload 7
    //   195: invokevirtual 103	android/database/sqlite/SQLiteDatabase:close	()V
    //   198: iconst_1
    //   199: ireturn
    //   200: astore 7
    //   202: goto +164 -> 366
    //   205: astore 7
    //   207: aload 8
    //   209: ifnull +24 -> 233
    //   212: aload 8
    //   214: astore 6
    //   216: aload 8
    //   218: invokevirtual 164	android/database/sqlite/SQLiteDatabase:inTransaction	()Z
    //   221: ifeq +12 -> 233
    //   224: aload 8
    //   226: astore 6
    //   228: aload 8
    //   230: invokevirtual 161	android/database/sqlite/SQLiteDatabase:endTransaction	()V
    //   233: aload 8
    //   235: astore 6
    //   237: aload_0
    //   238: invokevirtual 118	com/google/android/gms/measurement/internal/zzgo:zzq	()Lcom/google/android/gms/measurement/internal/zzer;
    //   241: invokevirtual 124	com/google/android/gms/measurement/internal/zzer:zze	()Lcom/google/android/gms/measurement/internal/zzet;
    //   244: ldc_w 342
    //   247: aload 7
    //   249: invokevirtual 169	com/google/android/gms/measurement/internal/zzet:zza	(Ljava/lang/String;Ljava/lang/Object;)V
    //   252: aload 8
    //   254: astore 6
    //   256: aload_0
    //   257: iconst_1
    //   258: putfield 77	com/google/android/gms/measurement/internal/zzen:zzb	Z
    //   261: iload_3
    //   262: istore_1
    //   263: aload 8
    //   265: ifnull +92 -> 357
    //   268: aload 8
    //   270: invokevirtual 103	android/database/sqlite/SQLiteDatabase:close	()V
    //   273: iload_3
    //   274: istore_1
    //   275: goto +82 -> 357
    //   278: iload_3
    //   279: i2l
    //   280: lstore 4
    //   282: aload 10
    //   284: astore 6
    //   286: lload 4
    //   288: invokestatic 175	android/os/SystemClock:sleep	(J)V
    //   291: iload_3
    //   292: bipush 20
    //   294: iadd
    //   295: istore_3
    //   296: iload_3
    //   297: istore_1
    //   298: aload 10
    //   300: ifnull +57 -> 357
    //   303: aload 10
    //   305: invokevirtual 103	android/database/sqlite/SQLiteDatabase:close	()V
    //   308: iload_3
    //   309: istore_1
    //   310: goto +47 -> 357
    //   313: astore 7
    //   315: aload 9
    //   317: astore 6
    //   319: aload_0
    //   320: invokevirtual 118	com/google/android/gms/measurement/internal/zzgo:zzq	()Lcom/google/android/gms/measurement/internal/zzer;
    //   323: invokevirtual 124	com/google/android/gms/measurement/internal/zzer:zze	()Lcom/google/android/gms/measurement/internal/zzet;
    //   326: ldc_w 342
    //   329: aload 7
    //   331: invokevirtual 169	com/google/android/gms/measurement/internal/zzet:zza	(Ljava/lang/String;Ljava/lang/Object;)V
    //   334: aload 9
    //   336: astore 6
    //   338: aload_0
    //   339: iconst_1
    //   340: putfield 77	com/google/android/gms/measurement/internal/zzen:zzb	Z
    //   343: iload_3
    //   344: istore_1
    //   345: aload 9
    //   347: ifnull +10 -> 357
    //   350: aload 9
    //   352: invokevirtual 103	android/database/sqlite/SQLiteDatabase:close	()V
    //   355: iload_3
    //   356: istore_1
    //   357: iload_2
    //   358: iconst_1
    //   359: iadd
    //   360: istore_2
    //   361: iload_1
    //   362: istore_3
    //   363: goto -337 -> 26
    //   366: aload 6
    //   368: ifnull +8 -> 376
    //   371: aload 6
    //   373: invokevirtual 103	android/database/sqlite/SQLiteDatabase:close	()V
    //   376: aload 7
    //   378: athrow
    //   379: aload_0
    //   380: invokevirtual 118	com/google/android/gms/measurement/internal/zzgo:zzq	()Lcom/google/android/gms/measurement/internal/zzer;
    //   383: invokevirtual 278	com/google/android/gms/measurement/internal/zzer:zzh	()Lcom/google/android/gms/measurement/internal/zzet;
    //   386: ldc_w 344
    //   389: invokevirtual 131	com/google/android/gms/measurement/internal/zzet:zza	(Ljava/lang/String;)V
    //   392: iconst_0
    //   393: ireturn
    //   394: astore 6
    //   396: goto -118 -> 278
    // Local variable table:
    //   start	length	slot	name	signature
    //   0	399	0	this	zzen
    //   262	100	1	i	int
    //   23	338	2	j	int
    //   25	338	3	k	int
    //   280	7	4	l	long
    //   41	331	6	localObject1	Object
    //   394	1	6	localSQLiteDatabaseLockedException	android.database.sqlite.SQLiteDatabaseLockedException
    //   47	147	7	localSQLiteDatabase	SQLiteDatabase
    //   200	1	7	localObject2	Object
    //   205	43	7	localSQLiteException	SQLiteException
    //   313	64	7	localSQLiteFullException	android.database.sqlite.SQLiteFullException
    //   32	237	8	localObject3	Object
    //   35	316	9	localObject4	Object
    //   38	266	10	localObject5	Object
    // Exception table:
    //   from	to	target	type
    //   43	49	200	finally
    //   70	75	200	finally
    //   103	108	200	finally
    //   124	146	200	finally
    //   162	167	200	finally
    //   183	188	200	finally
    //   216	224	200	finally
    //   228	233	200	finally
    //   237	252	200	finally
    //   256	261	200	finally
    //   286	291	200	finally
    //   319	334	200	finally
    //   338	343	200	finally
    //   43	49	205	android/database/sqlite/SQLiteException
    //   70	75	205	android/database/sqlite/SQLiteException
    //   103	108	205	android/database/sqlite/SQLiteException
    //   124	146	205	android/database/sqlite/SQLiteException
    //   162	167	205	android/database/sqlite/SQLiteException
    //   183	188	205	android/database/sqlite/SQLiteException
    //   43	49	313	android/database/sqlite/SQLiteFullException
    //   70	75	313	android/database/sqlite/SQLiteFullException
    //   103	108	313	android/database/sqlite/SQLiteFullException
    //   124	146	313	android/database/sqlite/SQLiteFullException
    //   162	167	313	android/database/sqlite/SQLiteFullException
    //   183	188	313	android/database/sqlite/SQLiteFullException
    //   43	49	394	android/database/sqlite/SQLiteDatabaseLockedException
    //   70	75	394	android/database/sqlite/SQLiteDatabaseLockedException
    //   103	108	394	android/database/sqlite/SQLiteDatabaseLockedException
    //   124	146	394	android/database/sqlite/SQLiteDatabaseLockedException
    //   162	167	394	android/database/sqlite/SQLiteDatabaseLockedException
    //   183	188	394	android/database/sqlite/SQLiteDatabaseLockedException
  }
  
  protected final boolean zzy()
  {
    return false;
  }
}


/* Location:              C:\Users\adinb\Downloads\dex2jar-2.0\dex2jar-2.0\0x89a2c000-dex2jar.jar!\com\google\android\gms\measurement\internal\zzen.class
 * Java compiler version: 6 (50.0)
 * JD-Core Version:       0.7.1
 */