package com.google.android.gms.measurement.internal;

import com.google.android.gms.common.internal.Preconditions;
import java.net.URL;
import java.util.Map;

final class zzey
  implements Runnable
{
  private final URL zza;
  private final byte[] zzb;
  private final zzew zzc;
  private final String zzd;
  private final Map<String, String> zze;
  
  public zzey(String paramString, URL paramURL, byte[] paramArrayOfByte, Map<String, String> paramMap, zzew paramzzew)
  {
    Preconditions.checkNotEmpty(paramURL);
    Preconditions.checkNotNull(paramArrayOfByte);
    Object localObject;
    Preconditions.checkNotNull(localObject);
    this.zza = paramArrayOfByte;
    this.zzb = paramMap;
    this.zzc = ((zzew)localObject);
    this.zzd = paramURL;
    this.zze = paramzzew;
  }
  
  /* Error */
  public final void run()
  {
    // Byte code:
    //   0: aload_0
    //   1: getfield 23	com/google/android/gms/measurement/internal/zzey:zzf	Lcom/google/android/gms/measurement/internal/zzeu;
    //   4: invokevirtual 56	com/google/android/gms/measurement/internal/zzgo:zzb	()V
    //   7: aconst_null
    //   8: astore 5
    //   10: aconst_null
    //   11: astore 8
    //   13: aconst_null
    //   14: astore 6
    //   16: aconst_null
    //   17: astore 7
    //   19: aload_0
    //   20: getfield 23	com/google/android/gms/measurement/internal/zzey:zzf	Lcom/google/android/gms/measurement/internal/zzeu;
    //   23: aload_0
    //   24: getfield 38	com/google/android/gms/measurement/internal/zzey:zza	Ljava/net/URL;
    //   27: invokevirtual 61	com/google/android/gms/measurement/internal/zzeu:zza	(Ljava/net/URL;)Ljava/net/HttpURLConnection;
    //   30: astore_2
    //   31: aload_0
    //   32: getfield 46	com/google/android/gms/measurement/internal/zzey:zze	Ljava/util/Map;
    //   35: ifnull +65 -> 100
    //   38: aload_0
    //   39: getfield 46	com/google/android/gms/measurement/internal/zzey:zze	Ljava/util/Map;
    //   42: invokeinterface 67 1 0
    //   47: invokeinterface 73 1 0
    //   52: astore_3
    //   53: aload_3
    //   54: invokeinterface 79 1 0
    //   59: ifeq +41 -> 100
    //   62: aload_3
    //   63: invokeinterface 83 1 0
    //   68: checkcast 85	java/util/Map$Entry
    //   71: astore 4
    //   73: aload_2
    //   74: aload 4
    //   76: invokeinterface 88 1 0
    //   81: checkcast 90	java/lang/String
    //   84: aload 4
    //   86: invokeinterface 93 1 0
    //   91: checkcast 90	java/lang/String
    //   94: invokevirtual 99	java/net/HttpURLConnection:addRequestProperty	(Ljava/lang/String;Ljava/lang/String;)V
    //   97: goto -44 -> 53
    //   100: aload_0
    //   101: getfield 40	com/google/android/gms/measurement/internal/zzey:zzb	[B
    //   104: ifnull +95 -> 199
    //   107: aload_0
    //   108: getfield 23	com/google/android/gms/measurement/internal/zzey:zzf	Lcom/google/android/gms/measurement/internal/zzeu;
    //   111: invokevirtual 105	com/google/android/gms/measurement/internal/zzkg:f_	()Lcom/google/android/gms/measurement/internal/zzks;
    //   114: aload_0
    //   115: getfield 40	com/google/android/gms/measurement/internal/zzey:zzb	[B
    //   118: invokevirtual 110	com/google/android/gms/measurement/internal/zzks:zzc	([B)[B
    //   121: astore 4
    //   123: aload_0
    //   124: getfield 23	com/google/android/gms/measurement/internal/zzey:zzf	Lcom/google/android/gms/measurement/internal/zzeu;
    //   127: invokevirtual 114	com/google/android/gms/measurement/internal/zzgo:zzq	()Lcom/google/android/gms/measurement/internal/zzer;
    //   130: invokevirtual 120	com/google/android/gms/measurement/internal/zzer:zzw	()Lcom/google/android/gms/measurement/internal/zzet;
    //   133: ldc 122
    //   135: aload 4
    //   137: arraylength
    //   138: invokestatic 128	java/lang/Integer:valueOf	(I)Ljava/lang/Integer;
    //   141: invokevirtual 133	com/google/android/gms/measurement/internal/zzet:zza	(Ljava/lang/String;Ljava/lang/Object;)V
    //   144: aload_2
    //   145: iconst_1
    //   146: invokevirtual 137	java/net/HttpURLConnection:setDoOutput	(Z)V
    //   149: aload_2
    //   150: ldc -117
    //   152: ldc -115
    //   154: invokevirtual 99	java/net/HttpURLConnection:addRequestProperty	(Ljava/lang/String;Ljava/lang/String;)V
    //   157: aload_2
    //   158: aload 4
    //   160: arraylength
    //   161: invokevirtual 145	java/net/HttpURLConnection:setFixedLengthStreamingMode	(I)V
    //   164: aload_2
    //   165: invokevirtual 148	java/net/HttpURLConnection:connect	()V
    //   168: aload_2
    //   169: invokevirtual 152	java/net/HttpURLConnection:getOutputStream	()Ljava/io/OutputStream;
    //   172: astore_3
    //   173: aload_3
    //   174: aload 4
    //   176: invokevirtual 158	java/io/OutputStream:write	([B)V
    //   179: aload_3
    //   180: invokevirtual 161	java/io/OutputStream:close	()V
    //   183: goto +16 -> 199
    //   186: astore 4
    //   188: aload_2
    //   189: astore 5
    //   191: goto +137 -> 328
    //   194: astore 4
    //   196: goto +223 -> 419
    //   199: aload_2
    //   200: invokevirtual 165	java/net/HttpURLConnection:getResponseCode	()I
    //   203: istore_1
    //   204: aload_2
    //   205: invokevirtual 169	java/net/HttpURLConnection:getHeaderFields	()Ljava/util/Map;
    //   208: astore_3
    //   209: aload_0
    //   210: getfield 23	com/google/android/gms/measurement/internal/zzey:zzf	Lcom/google/android/gms/measurement/internal/zzeu;
    //   213: aload_2
    //   214: invokestatic 172	com/google/android/gms/measurement/internal/zzeu:zza	(Lcom/google/android/gms/measurement/internal/zzeu;Ljava/net/HttpURLConnection;)[B
    //   217: astore 4
    //   219: aload_2
    //   220: ifnull +7 -> 227
    //   223: aload_2
    //   224: invokevirtual 175	java/net/HttpURLConnection:disconnect	()V
    //   227: aload_0
    //   228: getfield 23	com/google/android/gms/measurement/internal/zzey:zzf	Lcom/google/android/gms/measurement/internal/zzeu;
    //   231: invokevirtual 179	com/google/android/gms/measurement/internal/zzgo:zzp	()Lcom/google/android/gms/measurement/internal/zzfo;
    //   234: new 181	com/google/android/gms/measurement/internal/zzez
    //   237: dup
    //   238: aload_0
    //   239: getfield 44	com/google/android/gms/measurement/internal/zzey:zzd	Ljava/lang/String;
    //   242: aload_0
    //   243: getfield 42	com/google/android/gms/measurement/internal/zzey:zzc	Lcom/google/android/gms/measurement/internal/zzew;
    //   246: iload_1
    //   247: aconst_null
    //   248: aload 4
    //   250: aload_3
    //   251: aconst_null
    //   252: invokespecial 184	com/google/android/gms/measurement/internal/zzez:<init>	(Ljava/lang/String;Lcom/google/android/gms/measurement/internal/zzew;ILjava/lang/Throwable;[BLjava/util/Map;Lcom/google/android/gms/measurement/internal/zzex;)V
    //   255: invokevirtual 189	com/google/android/gms/measurement/internal/zzfo:zza	(Ljava/lang/Runnable;)V
    //   258: return
    //   259: astore 4
    //   261: aload_3
    //   262: astore 6
    //   264: aload 5
    //   266: astore_3
    //   267: aload_2
    //   268: astore 5
    //   270: aload 6
    //   272: astore_2
    //   273: goto +59 -> 332
    //   276: astore 4
    //   278: goto +24 -> 302
    //   281: astore 4
    //   283: aconst_null
    //   284: astore 6
    //   286: aload 5
    //   288: astore_3
    //   289: aload_2
    //   290: astore 5
    //   292: aload 6
    //   294: astore_2
    //   295: goto +37 -> 332
    //   298: astore 4
    //   300: aconst_null
    //   301: astore_3
    //   302: aload_3
    //   303: astore 5
    //   305: goto +122 -> 427
    //   308: astore_3
    //   309: goto +10 -> 319
    //   312: astore_3
    //   313: goto +100 -> 413
    //   316: astore_3
    //   317: aconst_null
    //   318: astore_2
    //   319: aload_2
    //   320: astore 5
    //   322: aload_3
    //   323: astore 4
    //   325: aload 7
    //   327: astore_3
    //   328: aconst_null
    //   329: astore_2
    //   330: iconst_0
    //   331: istore_1
    //   332: aload_3
    //   333: ifnull +34 -> 367
    //   336: aload_3
    //   337: invokevirtual 161	java/io/OutputStream:close	()V
    //   340: goto +27 -> 367
    //   343: astore_3
    //   344: aload_0
    //   345: getfield 23	com/google/android/gms/measurement/internal/zzey:zzf	Lcom/google/android/gms/measurement/internal/zzeu;
    //   348: invokevirtual 114	com/google/android/gms/measurement/internal/zzgo:zzq	()Lcom/google/android/gms/measurement/internal/zzer;
    //   351: invokevirtual 191	com/google/android/gms/measurement/internal/zzer:zze	()Lcom/google/android/gms/measurement/internal/zzet;
    //   354: ldc -63
    //   356: aload_0
    //   357: getfield 44	com/google/android/gms/measurement/internal/zzey:zzd	Ljava/lang/String;
    //   360: invokestatic 196	com/google/android/gms/measurement/internal/zzer:zza	(Ljava/lang/String;)Ljava/lang/Object;
    //   363: aload_3
    //   364: invokevirtual 199	com/google/android/gms/measurement/internal/zzet:zza	(Ljava/lang/String;Ljava/lang/Object;Ljava/lang/Object;)V
    //   367: aload 5
    //   369: ifnull +8 -> 377
    //   372: aload 5
    //   374: invokevirtual 175	java/net/HttpURLConnection:disconnect	()V
    //   377: aload_0
    //   378: getfield 23	com/google/android/gms/measurement/internal/zzey:zzf	Lcom/google/android/gms/measurement/internal/zzeu;
    //   381: invokevirtual 179	com/google/android/gms/measurement/internal/zzgo:zzp	()Lcom/google/android/gms/measurement/internal/zzfo;
    //   384: new 181	com/google/android/gms/measurement/internal/zzez
    //   387: dup
    //   388: aload_0
    //   389: getfield 44	com/google/android/gms/measurement/internal/zzey:zzd	Ljava/lang/String;
    //   392: aload_0
    //   393: getfield 42	com/google/android/gms/measurement/internal/zzey:zzc	Lcom/google/android/gms/measurement/internal/zzew;
    //   396: iload_1
    //   397: aconst_null
    //   398: aconst_null
    //   399: aload_2
    //   400: aconst_null
    //   401: invokespecial 184	com/google/android/gms/measurement/internal/zzez:<init>	(Ljava/lang/String;Lcom/google/android/gms/measurement/internal/zzew;ILjava/lang/Throwable;[BLjava/util/Map;Lcom/google/android/gms/measurement/internal/zzex;)V
    //   404: invokevirtual 189	com/google/android/gms/measurement/internal/zzfo:zza	(Ljava/lang/Runnable;)V
    //   407: aload 4
    //   409: athrow
    //   410: astore_3
    //   411: aconst_null
    //   412: astore_2
    //   413: aload_3
    //   414: astore 4
    //   416: aload 8
    //   418: astore_3
    //   419: aconst_null
    //   420: astore 5
    //   422: iconst_0
    //   423: istore_1
    //   424: aload_3
    //   425: astore 6
    //   427: aload 6
    //   429: ifnull +35 -> 464
    //   432: aload 6
    //   434: invokevirtual 161	java/io/OutputStream:close	()V
    //   437: goto +27 -> 464
    //   440: astore_3
    //   441: aload_0
    //   442: getfield 23	com/google/android/gms/measurement/internal/zzey:zzf	Lcom/google/android/gms/measurement/internal/zzeu;
    //   445: invokevirtual 114	com/google/android/gms/measurement/internal/zzgo:zzq	()Lcom/google/android/gms/measurement/internal/zzer;
    //   448: invokevirtual 191	com/google/android/gms/measurement/internal/zzer:zze	()Lcom/google/android/gms/measurement/internal/zzet;
    //   451: ldc -63
    //   453: aload_0
    //   454: getfield 44	com/google/android/gms/measurement/internal/zzey:zzd	Ljava/lang/String;
    //   457: invokestatic 196	com/google/android/gms/measurement/internal/zzer:zza	(Ljava/lang/String;)Ljava/lang/Object;
    //   460: aload_3
    //   461: invokevirtual 199	com/google/android/gms/measurement/internal/zzet:zza	(Ljava/lang/String;Ljava/lang/Object;Ljava/lang/Object;)V
    //   464: aload_2
    //   465: ifnull +7 -> 472
    //   468: aload_2
    //   469: invokevirtual 175	java/net/HttpURLConnection:disconnect	()V
    //   472: aload_0
    //   473: getfield 23	com/google/android/gms/measurement/internal/zzey:zzf	Lcom/google/android/gms/measurement/internal/zzeu;
    //   476: invokevirtual 179	com/google/android/gms/measurement/internal/zzgo:zzp	()Lcom/google/android/gms/measurement/internal/zzfo;
    //   479: new 181	com/google/android/gms/measurement/internal/zzez
    //   482: dup
    //   483: aload_0
    //   484: getfield 44	com/google/android/gms/measurement/internal/zzey:zzd	Ljava/lang/String;
    //   487: aload_0
    //   488: getfield 42	com/google/android/gms/measurement/internal/zzey:zzc	Lcom/google/android/gms/measurement/internal/zzew;
    //   491: iload_1
    //   492: aload 4
    //   494: aconst_null
    //   495: aload 5
    //   497: aconst_null
    //   498: invokespecial 184	com/google/android/gms/measurement/internal/zzez:<init>	(Ljava/lang/String;Lcom/google/android/gms/measurement/internal/zzew;ILjava/lang/Throwable;[BLjava/util/Map;Lcom/google/android/gms/measurement/internal/zzex;)V
    //   501: invokevirtual 189	com/google/android/gms/measurement/internal/zzfo:zza	(Ljava/lang/Runnable;)V
    //   504: return
    // Local variable table:
    //   start	length	slot	name	signature
    //   0	505	0	this	zzey
    //   203	289	1	i	int
    //   30	439	2	localObject1	Object
    //   52	251	3	localObject2	Object
    //   308	1	3	localObject3	Object
    //   312	1	3	localIOException1	java.io.IOException
    //   316	7	3	localObject4	Object
    //   327	10	3	localObject5	Object
    //   343	21	3	localIOException2	java.io.IOException
    //   410	4	3	localIOException3	java.io.IOException
    //   418	7	3	localObject6	Object
    //   440	21	3	localIOException4	java.io.IOException
    //   71	104	4	localObject7	Object
    //   186	1	4	localObject8	Object
    //   194	1	4	localIOException5	java.io.IOException
    //   217	32	4	arrayOfByte	byte[]
    //   259	1	4	localObject9	Object
    //   276	1	4	localIOException6	java.io.IOException
    //   281	1	4	localObject10	Object
    //   298	1	4	localIOException7	java.io.IOException
    //   323	170	4	localObject11	Object
    //   8	488	5	localObject12	Object
    //   14	419	6	localObject13	Object
    //   17	309	7	localObject14	Object
    //   11	406	8	localObject15	Object
    // Exception table:
    //   from	to	target	type
    //   173	183	186	finally
    //   173	183	194	java/io/IOException
    //   209	219	259	finally
    //   209	219	276	java/io/IOException
    //   204	209	281	finally
    //   204	209	298	java/io/IOException
    //   31	53	308	finally
    //   53	97	308	finally
    //   100	173	308	finally
    //   199	204	308	finally
    //   31	53	312	java/io/IOException
    //   53	97	312	java/io/IOException
    //   100	173	312	java/io/IOException
    //   199	204	312	java/io/IOException
    //   19	31	316	finally
    //   336	340	343	java/io/IOException
    //   19	31	410	java/io/IOException
    //   432	437	440	java/io/IOException
  }
}


/* Location:              C:\Users\adinb\Downloads\dex2jar-2.0\dex2jar-2.0\0x89a2c000-dex2jar.jar!\com\google\android\gms\measurement\internal\zzey.class
 * Java compiler version: 6 (50.0)
 * JD-Core Version:       0.7.1
 */