package com.google.android.gms.measurement.internal;

import java.util.concurrent.atomic.AtomicReference;

final class zzhq
  implements Runnable
{
  zzhq(zzgy paramzzgy, AtomicReference paramAtomicReference) {}
  
  /* Error */
  public final void run()
  {
    // Byte code:
    //   0: aload_0
    //   1: getfield 16	com/google/android/gms/measurement/internal/zzhq:zza	Ljava/util/concurrent/atomic/AtomicReference;
    //   4: astore_1
    //   5: aload_1
    //   6: monitorenter
    //   7: aload_0
    //   8: getfield 16	com/google/android/gms/measurement/internal/zzhq:zza	Ljava/util/concurrent/atomic/AtomicReference;
    //   11: aload_0
    //   12: getfield 14	com/google/android/gms/measurement/internal/zzhq:zzb	Lcom/google/android/gms/measurement/internal/zzgy;
    //   15: invokevirtual 27	com/google/android/gms/measurement/internal/zzgo:zzs	()Lcom/google/android/gms/measurement/internal/zzy;
    //   18: aload_0
    //   19: getfield 14	com/google/android/gms/measurement/internal/zzhq:zzb	Lcom/google/android/gms/measurement/internal/zzgy;
    //   22: invokevirtual 33	com/google/android/gms/measurement/internal/zzd:zzf	()Lcom/google/android/gms/measurement/internal/zzek;
    //   25: invokevirtual 39	com/google/android/gms/measurement/internal/zzek:zzaa	()Ljava/lang/String;
    //   28: getstatic 45	com/google/android/gms/measurement/internal/zzat:zzal	Lcom/google/android/gms/measurement/internal/zzeg;
    //   31: invokevirtual 50	com/google/android/gms/measurement/internal/zzy:zza	(Ljava/lang/String;Lcom/google/android/gms/measurement/internal/zzeg;)J
    //   34: invokestatic 56	java/lang/Long:valueOf	(J)Ljava/lang/Long;
    //   37: invokevirtual 62	java/util/concurrent/atomic/AtomicReference:set	(Ljava/lang/Object;)V
    //   40: aload_0
    //   41: getfield 16	com/google/android/gms/measurement/internal/zzhq:zza	Ljava/util/concurrent/atomic/AtomicReference;
    //   44: invokevirtual 65	java/lang/Object:notify	()V
    //   47: aload_1
    //   48: monitorexit
    //   49: return
    //   50: astore_2
    //   51: aload_0
    //   52: getfield 16	com/google/android/gms/measurement/internal/zzhq:zza	Ljava/util/concurrent/atomic/AtomicReference;
    //   55: invokevirtual 65	java/lang/Object:notify	()V
    //   58: aload_2
    //   59: athrow
    //   60: astore_2
    //   61: aload_1
    //   62: monitorexit
    //   63: aload_2
    //   64: athrow
    // Local variable table:
    //   start	length	slot	name	signature
    //   0	65	0	this	zzhq
    //   4	58	1	localAtomicReference	AtomicReference
    //   50	9	2	localObject1	Object
    //   60	4	2	localObject2	Object
    // Exception table:
    //   from	to	target	type
    //   7	40	50	finally
    //   40	49	60	finally
    //   51	60	60	finally
    //   61	63	60	finally
  }
}


/* Location:              C:\Users\adinb\Downloads\dex2jar-2.0\dex2jar-2.0\0x89a2c000-dex2jar.jar!\com\google\android\gms\measurement\internal\zzhq.class
 * Java compiler version: 6 (50.0)
 * JD-Core Version:       0.7.1
 */