package com.google.android.gms.measurement.internal;

import com.google.android.gms.common.internal.Preconditions;
import java.net.URL;
import java.util.List;
import java.util.Map;

final class zzic
  implements Runnable
{
  private final URL zza;
  private final byte[] zzb;
  private final zzid zzc;
  private final String zzd;
  private final Map<String, String> zze;
  
  public zzic(String paramString, URL paramURL, byte[] paramArrayOfByte, Map<String, String> paramMap, zzid paramzzid)
  {
    Preconditions.checkNotEmpty(paramURL);
    Preconditions.checkNotNull(paramArrayOfByte);
    Object localObject;
    Preconditions.checkNotNull(localObject);
    this.zza = paramArrayOfByte;
    this.zzb = null;
    this.zzc = ((zzid)localObject);
    this.zzd = paramURL;
    this.zze = null;
  }
  
  private final void zzb(int paramInt, Exception paramException, byte[] paramArrayOfByte, Map<String, List<String>> paramMap)
  {
    this.zzf.zzp().zza(new zzif(this, paramInt, paramException, paramArrayOfByte, paramMap));
  }
  
  /* Error */
  public final void run()
  {
    // Byte code:
    //   0: aload_0
    //   1: getfield 23	com/google/android/gms/measurement/internal/zzic:zzf	Lcom/google/android/gms/measurement/internal/zzia;
    //   4: invokevirtual 72	com/google/android/gms/measurement/internal/zzgo:zzb	()V
    //   7: iconst_0
    //   8: istore_3
    //   9: iconst_0
    //   10: istore_1
    //   11: iconst_0
    //   12: istore 4
    //   14: iconst_0
    //   15: istore_2
    //   16: aload_0
    //   17: getfield 23	com/google/android/gms/measurement/internal/zzic:zzf	Lcom/google/android/gms/measurement/internal/zzia;
    //   20: aload_0
    //   21: getfield 38	com/google/android/gms/measurement/internal/zzic:zza	Ljava/net/URL;
    //   24: invokevirtual 77	com/google/android/gms/measurement/internal/zzia:zza	(Ljava/net/URL;)Ljava/net/HttpURLConnection;
    //   27: astore 5
    //   29: aload 5
    //   31: invokevirtual 83	java/net/HttpURLConnection:getResponseCode	()I
    //   34: istore_1
    //   35: iload_1
    //   36: istore_2
    //   37: iload_1
    //   38: istore_3
    //   39: aload 5
    //   41: invokevirtual 87	java/net/HttpURLConnection:getHeaderFields	()Ljava/util/Map;
    //   44: astore 6
    //   46: aload_0
    //   47: getfield 23	com/google/android/gms/measurement/internal/zzic:zzf	Lcom/google/android/gms/measurement/internal/zzia;
    //   50: aload 5
    //   52: invokestatic 90	com/google/android/gms/measurement/internal/zzia:zza	(Lcom/google/android/gms/measurement/internal/zzia;Ljava/net/HttpURLConnection;)[B
    //   55: astore 7
    //   57: aload 5
    //   59: ifnull +8 -> 67
    //   62: aload 5
    //   64: invokevirtual 93	java/net/HttpURLConnection:disconnect	()V
    //   67: aload_0
    //   68: iload_1
    //   69: aconst_null
    //   70: aload 7
    //   72: aload 6
    //   74: invokespecial 95	com/google/android/gms/measurement/internal/zzic:zzb	(ILjava/lang/Exception;[BLjava/util/Map;)V
    //   77: return
    //   78: astore 8
    //   80: aload 5
    //   82: astore 7
    //   84: aload 6
    //   86: astore 5
    //   88: aload 8
    //   90: astore 6
    //   92: goto +65 -> 157
    //   95: astore 8
    //   97: aload 5
    //   99: astore 7
    //   101: aload 6
    //   103: astore 5
    //   105: aload 8
    //   107: astore 6
    //   109: goto +82 -> 191
    //   112: astore 6
    //   114: aconst_null
    //   115: astore 8
    //   117: iload_2
    //   118: istore_1
    //   119: aload 5
    //   121: astore 7
    //   123: aload 8
    //   125: astore 5
    //   127: goto +30 -> 157
    //   130: astore 6
    //   132: aconst_null
    //   133: astore 8
    //   135: iload_3
    //   136: istore_1
    //   137: aload 5
    //   139: astore 7
    //   141: aload 8
    //   143: astore 5
    //   145: goto +46 -> 191
    //   148: astore 6
    //   150: aconst_null
    //   151: astore 7
    //   153: aload 7
    //   155: astore 5
    //   157: aload 7
    //   159: ifnull +8 -> 167
    //   162: aload 7
    //   164: invokevirtual 93	java/net/HttpURLConnection:disconnect	()V
    //   167: aload_0
    //   168: iload_1
    //   169: aconst_null
    //   170: aconst_null
    //   171: aload 5
    //   173: invokespecial 95	com/google/android/gms/measurement/internal/zzic:zzb	(ILjava/lang/Exception;[BLjava/util/Map;)V
    //   176: aload 6
    //   178: athrow
    //   179: astore 6
    //   181: aconst_null
    //   182: astore 7
    //   184: aload 7
    //   186: astore 5
    //   188: iload 4
    //   190: istore_1
    //   191: aload 7
    //   193: ifnull +8 -> 201
    //   196: aload 7
    //   198: invokevirtual 93	java/net/HttpURLConnection:disconnect	()V
    //   201: aload_0
    //   202: iload_1
    //   203: aload 6
    //   205: aconst_null
    //   206: aload 5
    //   208: invokespecial 95	com/google/android/gms/measurement/internal/zzic:zzb	(ILjava/lang/Exception;[BLjava/util/Map;)V
    //   211: return
    // Local variable table:
    //   start	length	slot	name	signature
    //   0	212	0	this	zzic
    //   10	193	1	i	int
    //   15	103	2	j	int
    //   8	128	3	k	int
    //   12	177	4	m	int
    //   27	180	5	localObject1	Object
    //   44	64	6	localObject2	Object
    //   112	1	6	localObject3	Object
    //   130	1	6	localIOException1	java.io.IOException
    //   148	29	6	localObject4	Object
    //   179	25	6	localIOException2	java.io.IOException
    //   55	142	7	localObject5	Object
    //   78	11	8	localObject6	Object
    //   95	11	8	localIOException3	java.io.IOException
    //   115	27	8	localObject7	Object
    // Exception table:
    //   from	to	target	type
    //   46	57	78	finally
    //   46	57	95	java/io/IOException
    //   29	35	112	finally
    //   39	46	112	finally
    //   29	35	130	java/io/IOException
    //   39	46	130	java/io/IOException
    //   16	29	148	finally
    //   16	29	179	java/io/IOException
  }
}


/* Location:              C:\Users\adinb\Downloads\dex2jar-2.0\dex2jar-2.0\0x89a2c000-dex2jar.jar!\com\google\android\gms\measurement\internal\zzic.class
 * Java compiler version: 6 (50.0)
 * JD-Core Version:       0.7.1
 */