package com.google.android.gms.measurement.internal;

import com.google.android.gms.internal.measurement.zzw;

final class zziq
  implements Runnable
{
  zziq(zzio paramzzio, String paramString1, String paramString2, boolean paramBoolean, zzn paramzzn, zzw paramzzw) {}
  
  /* Error */
  public final void run()
  {
    // Byte code:
    //   0: new 40	android/os/Bundle
    //   3: dup
    //   4: invokespecial 41	android/os/Bundle:<init>	()V
    //   7: astore_3
    //   8: aload_3
    //   9: astore_1
    //   10: aload_3
    //   11: astore_2
    //   12: aload_0
    //   13: getfield 21	com/google/android/gms/measurement/internal/zziq:zzf	Lcom/google/android/gms/measurement/internal/zzio;
    //   16: invokestatic 46	com/google/android/gms/measurement/internal/zzio:zzd	(Lcom/google/android/gms/measurement/internal/zzio;)Lcom/google/android/gms/measurement/internal/zzej;
    //   19: astore 4
    //   21: aload 4
    //   23: ifnonnull +46 -> 69
    //   26: aload_3
    //   27: astore_1
    //   28: aload_3
    //   29: astore_2
    //   30: aload_0
    //   31: getfield 21	com/google/android/gms/measurement/internal/zziq:zzf	Lcom/google/android/gms/measurement/internal/zzio;
    //   34: invokevirtual 52	com/google/android/gms/measurement/internal/zzgo:zzq	()Lcom/google/android/gms/measurement/internal/zzer;
    //   37: invokevirtual 57	com/google/android/gms/measurement/internal/zzer:zze	()Lcom/google/android/gms/measurement/internal/zzet;
    //   40: ldc 59
    //   42: aload_0
    //   43: getfield 23	com/google/android/gms/measurement/internal/zziq:zza	Ljava/lang/String;
    //   46: aload_0
    //   47: getfield 25	com/google/android/gms/measurement/internal/zziq:zzb	Ljava/lang/String;
    //   50: invokevirtual 64	com/google/android/gms/measurement/internal/zzet:zza	(Ljava/lang/String;Ljava/lang/Object;Ljava/lang/Object;)V
    //   53: aload_0
    //   54: getfield 21	com/google/android/gms/measurement/internal/zziq:zzf	Lcom/google/android/gms/measurement/internal/zzio;
    //   57: invokevirtual 68	com/google/android/gms/measurement/internal/zzgo:zzo	()Lcom/google/android/gms/measurement/internal/zzkw;
    //   60: aload_0
    //   61: getfield 31	com/google/android/gms/measurement/internal/zziq:zze	Lcom/google/android/gms/internal/measurement/zzw;
    //   64: aload_3
    //   65: invokevirtual 73	com/google/android/gms/measurement/internal/zzkw:zza	(Lcom/google/android/gms/internal/measurement/zzw;Landroid/os/Bundle;)V
    //   68: return
    //   69: aload_3
    //   70: astore_1
    //   71: aload_3
    //   72: astore_2
    //   73: aload 4
    //   75: aload_0
    //   76: getfield 23	com/google/android/gms/measurement/internal/zziq:zza	Ljava/lang/String;
    //   79: aload_0
    //   80: getfield 25	com/google/android/gms/measurement/internal/zziq:zzb	Ljava/lang/String;
    //   83: aload_0
    //   84: getfield 27	com/google/android/gms/measurement/internal/zziq:zzc	Z
    //   87: aload_0
    //   88: getfield 29	com/google/android/gms/measurement/internal/zziq:zzd	Lcom/google/android/gms/measurement/internal/zzn;
    //   91: invokeinterface 78 5 0
    //   96: invokestatic 81	com/google/android/gms/measurement/internal/zzkw:zza	(Ljava/util/List;)Landroid/os/Bundle;
    //   99: astore_3
    //   100: aload_3
    //   101: astore_1
    //   102: aload_3
    //   103: astore_2
    //   104: aload_0
    //   105: getfield 21	com/google/android/gms/measurement/internal/zziq:zzf	Lcom/google/android/gms/measurement/internal/zzio;
    //   108: invokestatic 84	com/google/android/gms/measurement/internal/zzio:zze	(Lcom/google/android/gms/measurement/internal/zzio;)V
    //   111: aload_0
    //   112: getfield 21	com/google/android/gms/measurement/internal/zziq:zzf	Lcom/google/android/gms/measurement/internal/zzio;
    //   115: invokevirtual 68	com/google/android/gms/measurement/internal/zzgo:zzo	()Lcom/google/android/gms/measurement/internal/zzkw;
    //   118: aload_0
    //   119: getfield 31	com/google/android/gms/measurement/internal/zziq:zze	Lcom/google/android/gms/internal/measurement/zzw;
    //   122: aload_3
    //   123: invokevirtual 73	com/google/android/gms/measurement/internal/zzkw:zza	(Lcom/google/android/gms/internal/measurement/zzw;Landroid/os/Bundle;)V
    //   126: return
    //   127: astore_2
    //   128: goto +42 -> 170
    //   131: astore_3
    //   132: aload_2
    //   133: astore_1
    //   134: aload_0
    //   135: getfield 21	com/google/android/gms/measurement/internal/zziq:zzf	Lcom/google/android/gms/measurement/internal/zzio;
    //   138: invokevirtual 52	com/google/android/gms/measurement/internal/zzgo:zzq	()Lcom/google/android/gms/measurement/internal/zzer;
    //   141: invokevirtual 57	com/google/android/gms/measurement/internal/zzer:zze	()Lcom/google/android/gms/measurement/internal/zzet;
    //   144: ldc 86
    //   146: aload_0
    //   147: getfield 23	com/google/android/gms/measurement/internal/zziq:zza	Ljava/lang/String;
    //   150: aload_3
    //   151: invokevirtual 64	com/google/android/gms/measurement/internal/zzet:zza	(Ljava/lang/String;Ljava/lang/Object;Ljava/lang/Object;)V
    //   154: aload_0
    //   155: getfield 21	com/google/android/gms/measurement/internal/zziq:zzf	Lcom/google/android/gms/measurement/internal/zzio;
    //   158: invokevirtual 68	com/google/android/gms/measurement/internal/zzgo:zzo	()Lcom/google/android/gms/measurement/internal/zzkw;
    //   161: aload_0
    //   162: getfield 31	com/google/android/gms/measurement/internal/zziq:zze	Lcom/google/android/gms/internal/measurement/zzw;
    //   165: aload_2
    //   166: invokevirtual 73	com/google/android/gms/measurement/internal/zzkw:zza	(Lcom/google/android/gms/internal/measurement/zzw;Landroid/os/Bundle;)V
    //   169: return
    //   170: aload_0
    //   171: getfield 21	com/google/android/gms/measurement/internal/zziq:zzf	Lcom/google/android/gms/measurement/internal/zzio;
    //   174: invokevirtual 68	com/google/android/gms/measurement/internal/zzgo:zzo	()Lcom/google/android/gms/measurement/internal/zzkw;
    //   177: aload_0
    //   178: getfield 31	com/google/android/gms/measurement/internal/zziq:zze	Lcom/google/android/gms/internal/measurement/zzw;
    //   181: aload_1
    //   182: invokevirtual 73	com/google/android/gms/measurement/internal/zzkw:zza	(Lcom/google/android/gms/internal/measurement/zzw;Landroid/os/Bundle;)V
    //   185: aload_2
    //   186: athrow
    // Local variable table:
    //   start	length	slot	name	signature
    //   0	187	0	this	zziq
    //   9	173	1	localObject	Object
    //   11	93	2	localBundle1	android.os.Bundle
    //   127	59	2	localBundle2	android.os.Bundle
    //   7	116	3	localBundle3	android.os.Bundle
    //   131	20	3	localRemoteException	android.os.RemoteException
    //   19	55	4	localzzej	zzej
    // Exception table:
    //   from	to	target	type
    //   12	21	127	finally
    //   30	53	127	finally
    //   73	100	127	finally
    //   104	111	127	finally
    //   134	154	127	finally
    //   12	21	131	android/os/RemoteException
    //   30	53	131	android/os/RemoteException
    //   73	100	131	android/os/RemoteException
    //   104	111	131	android/os/RemoteException
  }
}


/* Location:              C:\Users\adinb\Downloads\dex2jar-2.0\dex2jar-2.0\0x89a2c000-dex2jar.jar!\com\google\android\gms\measurement\internal\zziq.class
 * Java compiler version: 6 (50.0)
 * JD-Core Version:       0.7.1
 */