package com.google.android.gms.common.api.internal;

abstract class zaau
  implements Runnable
{
  private zaau(zaak paramzaak) {}
  
  /* Error */
  public void run()
  {
    // Byte code:
    //   0: aload_0
    //   1: getfield 12	com/google/android/gms/common/api/internal/zaau:zagj	Lcom/google/android/gms/common/api/internal/zaak;
    //   4: invokestatic 28	com/google/android/gms/common/api/internal/zaak:zac	(Lcom/google/android/gms/common/api/internal/zaak;)Ljava/util/concurrent/locks/Lock;
    //   7: invokeinterface 33 1 0
    //   12: invokestatic 39	java/lang/Thread:interrupted	()Z
    //   15: istore_1
    //   16: iload_1
    //   17: ifeq +16 -> 33
    //   20: aload_0
    //   21: getfield 12	com/google/android/gms/common/api/internal/zaau:zagj	Lcom/google/android/gms/common/api/internal/zaak;
    //   24: invokestatic 28	com/google/android/gms/common/api/internal/zaak:zac	(Lcom/google/android/gms/common/api/internal/zaak;)Ljava/util/concurrent/locks/Lock;
    //   27: invokeinterface 42 1 0
    //   32: return
    //   33: aload_0
    //   34: invokevirtual 45	com/google/android/gms/common/api/internal/zaau:zaan	()V
    //   37: aload_0
    //   38: getfield 12	com/google/android/gms/common/api/internal/zaau:zagj	Lcom/google/android/gms/common/api/internal/zaak;
    //   41: invokestatic 28	com/google/android/gms/common/api/internal/zaak:zac	(Lcom/google/android/gms/common/api/internal/zaak;)Ljava/util/concurrent/locks/Lock;
    //   44: invokeinterface 42 1 0
    //   49: return
    //   50: astore_2
    //   51: goto +28 -> 79
    //   54: astore_2
    //   55: aload_0
    //   56: getfield 12	com/google/android/gms/common/api/internal/zaau:zagj	Lcom/google/android/gms/common/api/internal/zaak;
    //   59: invokestatic 49	com/google/android/gms/common/api/internal/zaak:zad	(Lcom/google/android/gms/common/api/internal/zaak;)Lcom/google/android/gms/common/api/internal/zabe;
    //   62: aload_2
    //   63: invokevirtual 55	com/google/android/gms/common/api/internal/zabe:zab	(Ljava/lang/RuntimeException;)V
    //   66: aload_0
    //   67: getfield 12	com/google/android/gms/common/api/internal/zaau:zagj	Lcom/google/android/gms/common/api/internal/zaak;
    //   70: invokestatic 28	com/google/android/gms/common/api/internal/zaak:zac	(Lcom/google/android/gms/common/api/internal/zaak;)Ljava/util/concurrent/locks/Lock;
    //   73: invokeinterface 42 1 0
    //   78: return
    //   79: aload_0
    //   80: getfield 12	com/google/android/gms/common/api/internal/zaau:zagj	Lcom/google/android/gms/common/api/internal/zaak;
    //   83: invokestatic 28	com/google/android/gms/common/api/internal/zaak:zac	(Lcom/google/android/gms/common/api/internal/zaak;)Ljava/util/concurrent/locks/Lock;
    //   86: invokeinterface 42 1 0
    //   91: aload_2
    //   92: athrow
    // Local variable table:
    //   start	length	slot	name	signature
    //   0	93	0	this	zaau
    //   15	2	1	bool	boolean
    //   50	1	2	localObject	Object
    //   54	38	2	localRuntimeException	RuntimeException
    // Exception table:
    //   from	to	target	type
    //   12	16	50	finally
    //   33	37	50	finally
    //   55	66	50	finally
    //   12	16	54	java/lang/RuntimeException
    //   33	37	54	java/lang/RuntimeException
  }
  
  protected abstract void zaan();
}


/* Location:              C:\Users\adinb\Downloads\dex2jar-2.0\dex2jar-2.0\0x89a2c000-dex2jar.jar!\com\google\android\gms\common\api\internal\zaau.class
 * Java compiler version: 6 (50.0)
 * JD-Core Version:       0.7.1
 */