package com.google.android.gms.common.api.internal;

import com.google.android.gms.common.api.Result;

final class zacn
  implements Runnable
{
  zacn(zacm paramzacm, Result paramResult) {}
  
  /* Error */
  public final void run()
  {
    // Byte code:
    //   0: getstatic 29	com/google/android/gms/common/api/internal/BasePendingResult:zadn	Ljava/lang/ThreadLocal;
    //   3: iconst_1
    //   4: invokestatic 35	java/lang/Boolean:valueOf	(Z)Ljava/lang/Boolean;
    //   7: invokevirtual 41	java/lang/ThreadLocal:set	(Ljava/lang/Object;)V
    //   10: aload_0
    //   11: getfield 14	com/google/android/gms/common/api/internal/zacn:zakw	Lcom/google/android/gms/common/api/internal/zacm;
    //   14: invokestatic 47	com/google/android/gms/common/api/internal/zacm:zac	(Lcom/google/android/gms/common/api/internal/zacm;)Lcom/google/android/gms/common/api/ResultTransform;
    //   17: aload_0
    //   18: getfield 16	com/google/android/gms/common/api/internal/zacn:zakv	Lcom/google/android/gms/common/api/Result;
    //   21: invokevirtual 53	com/google/android/gms/common/api/ResultTransform:onSuccess	(Lcom/google/android/gms/common/api/Result;)Lcom/google/android/gms/common/api/PendingResult;
    //   24: astore_1
    //   25: aload_0
    //   26: getfield 14	com/google/android/gms/common/api/internal/zacn:zakw	Lcom/google/android/gms/common/api/internal/zacm;
    //   29: invokestatic 57	com/google/android/gms/common/api/internal/zacm:zad	(Lcom/google/android/gms/common/api/internal/zacm;)Lcom/google/android/gms/common/api/internal/zaco;
    //   32: aload_0
    //   33: getfield 14	com/google/android/gms/common/api/internal/zacn:zakw	Lcom/google/android/gms/common/api/internal/zacm;
    //   36: invokestatic 57	com/google/android/gms/common/api/internal/zacm:zad	(Lcom/google/android/gms/common/api/internal/zacm;)Lcom/google/android/gms/common/api/internal/zaco;
    //   39: iconst_0
    //   40: aload_1
    //   41: invokevirtual 63	com/google/android/gms/common/api/internal/zaco:obtainMessage	(ILjava/lang/Object;)Landroid/os/Message;
    //   44: invokevirtual 67	com/google/android/gms/common/api/internal/zaco:sendMessage	(Landroid/os/Message;)Z
    //   47: pop
    //   48: getstatic 29	com/google/android/gms/common/api/internal/BasePendingResult:zadn	Ljava/lang/ThreadLocal;
    //   51: iconst_0
    //   52: invokestatic 35	java/lang/Boolean:valueOf	(Z)Ljava/lang/Boolean;
    //   55: invokevirtual 41	java/lang/ThreadLocal:set	(Ljava/lang/Object;)V
    //   58: aload_0
    //   59: getfield 14	com/google/android/gms/common/api/internal/zacn:zakw	Lcom/google/android/gms/common/api/internal/zacm;
    //   62: aload_0
    //   63: getfield 16	com/google/android/gms/common/api/internal/zacn:zakv	Lcom/google/android/gms/common/api/Result;
    //   66: invokestatic 70	com/google/android/gms/common/api/internal/zacm:zaa	(Lcom/google/android/gms/common/api/internal/zacm;Lcom/google/android/gms/common/api/Result;)V
    //   69: aload_0
    //   70: getfield 14	com/google/android/gms/common/api/internal/zacn:zakw	Lcom/google/android/gms/common/api/internal/zacm;
    //   73: invokestatic 74	com/google/android/gms/common/api/internal/zacm:zae	(Lcom/google/android/gms/common/api/internal/zacm;)Ljava/lang/ref/WeakReference;
    //   76: invokevirtual 80	java/lang/ref/WeakReference:get	()Ljava/lang/Object;
    //   79: checkcast 82	com/google/android/gms/common/api/GoogleApiClient
    //   82: astore_1
    //   83: aload_1
    //   84: ifnull +11 -> 95
    //   87: aload_1
    //   88: aload_0
    //   89: getfield 14	com/google/android/gms/common/api/internal/zacn:zakw	Lcom/google/android/gms/common/api/internal/zacm;
    //   92: invokevirtual 86	com/google/android/gms/common/api/GoogleApiClient:zab	(Lcom/google/android/gms/common/api/internal/zacm;)V
    //   95: return
    //   96: astore_1
    //   97: goto +75 -> 172
    //   100: astore_1
    //   101: aload_0
    //   102: getfield 14	com/google/android/gms/common/api/internal/zacn:zakw	Lcom/google/android/gms/common/api/internal/zacm;
    //   105: invokestatic 57	com/google/android/gms/common/api/internal/zacm:zad	(Lcom/google/android/gms/common/api/internal/zacm;)Lcom/google/android/gms/common/api/internal/zaco;
    //   108: aload_0
    //   109: getfield 14	com/google/android/gms/common/api/internal/zacn:zakw	Lcom/google/android/gms/common/api/internal/zacm;
    //   112: invokestatic 57	com/google/android/gms/common/api/internal/zacm:zad	(Lcom/google/android/gms/common/api/internal/zacm;)Lcom/google/android/gms/common/api/internal/zaco;
    //   115: iconst_1
    //   116: aload_1
    //   117: invokevirtual 63	com/google/android/gms/common/api/internal/zaco:obtainMessage	(ILjava/lang/Object;)Landroid/os/Message;
    //   120: invokevirtual 67	com/google/android/gms/common/api/internal/zaco:sendMessage	(Landroid/os/Message;)Z
    //   123: pop
    //   124: getstatic 29	com/google/android/gms/common/api/internal/BasePendingResult:zadn	Ljava/lang/ThreadLocal;
    //   127: iconst_0
    //   128: invokestatic 35	java/lang/Boolean:valueOf	(Z)Ljava/lang/Boolean;
    //   131: invokevirtual 41	java/lang/ThreadLocal:set	(Ljava/lang/Object;)V
    //   134: aload_0
    //   135: getfield 14	com/google/android/gms/common/api/internal/zacn:zakw	Lcom/google/android/gms/common/api/internal/zacm;
    //   138: aload_0
    //   139: getfield 16	com/google/android/gms/common/api/internal/zacn:zakv	Lcom/google/android/gms/common/api/Result;
    //   142: invokestatic 70	com/google/android/gms/common/api/internal/zacm:zaa	(Lcom/google/android/gms/common/api/internal/zacm;Lcom/google/android/gms/common/api/Result;)V
    //   145: aload_0
    //   146: getfield 14	com/google/android/gms/common/api/internal/zacn:zakw	Lcom/google/android/gms/common/api/internal/zacm;
    //   149: invokestatic 74	com/google/android/gms/common/api/internal/zacm:zae	(Lcom/google/android/gms/common/api/internal/zacm;)Ljava/lang/ref/WeakReference;
    //   152: invokevirtual 80	java/lang/ref/WeakReference:get	()Ljava/lang/Object;
    //   155: checkcast 82	com/google/android/gms/common/api/GoogleApiClient
    //   158: astore_1
    //   159: aload_1
    //   160: ifnull +11 -> 171
    //   163: aload_1
    //   164: aload_0
    //   165: getfield 14	com/google/android/gms/common/api/internal/zacn:zakw	Lcom/google/android/gms/common/api/internal/zacm;
    //   168: invokevirtual 86	com/google/android/gms/common/api/GoogleApiClient:zab	(Lcom/google/android/gms/common/api/internal/zacm;)V
    //   171: return
    //   172: getstatic 29	com/google/android/gms/common/api/internal/BasePendingResult:zadn	Ljava/lang/ThreadLocal;
    //   175: iconst_0
    //   176: invokestatic 35	java/lang/Boolean:valueOf	(Z)Ljava/lang/Boolean;
    //   179: invokevirtual 41	java/lang/ThreadLocal:set	(Ljava/lang/Object;)V
    //   182: aload_0
    //   183: getfield 14	com/google/android/gms/common/api/internal/zacn:zakw	Lcom/google/android/gms/common/api/internal/zacm;
    //   186: aload_0
    //   187: getfield 16	com/google/android/gms/common/api/internal/zacn:zakv	Lcom/google/android/gms/common/api/Result;
    //   190: invokestatic 70	com/google/android/gms/common/api/internal/zacm:zaa	(Lcom/google/android/gms/common/api/internal/zacm;Lcom/google/android/gms/common/api/Result;)V
    //   193: aload_0
    //   194: getfield 14	com/google/android/gms/common/api/internal/zacn:zakw	Lcom/google/android/gms/common/api/internal/zacm;
    //   197: invokestatic 74	com/google/android/gms/common/api/internal/zacm:zae	(Lcom/google/android/gms/common/api/internal/zacm;)Ljava/lang/ref/WeakReference;
    //   200: invokevirtual 80	java/lang/ref/WeakReference:get	()Ljava/lang/Object;
    //   203: checkcast 82	com/google/android/gms/common/api/GoogleApiClient
    //   206: astore_2
    //   207: aload_2
    //   208: ifnull +11 -> 219
    //   211: aload_2
    //   212: aload_0
    //   213: getfield 14	com/google/android/gms/common/api/internal/zacn:zakw	Lcom/google/android/gms/common/api/internal/zacm;
    //   216: invokevirtual 86	com/google/android/gms/common/api/GoogleApiClient:zab	(Lcom/google/android/gms/common/api/internal/zacm;)V
    //   219: aload_1
    //   220: athrow
    // Local variable table:
    //   start	length	slot	name	signature
    //   0	221	0	this	zacn
    //   24	64	1	localObject1	Object
    //   96	1	1	localObject2	Object
    //   100	17	1	localRuntimeException	RuntimeException
    //   158	62	1	localGoogleApiClient1	com.google.android.gms.common.api.GoogleApiClient
    //   206	6	2	localGoogleApiClient2	com.google.android.gms.common.api.GoogleApiClient
    // Exception table:
    //   from	to	target	type
    //   0	48	96	finally
    //   101	124	96	finally
    //   0	48	100	java/lang/RuntimeException
  }
}


/* Location:              C:\Users\adinb\Downloads\dex2jar-2.0\dex2jar-2.0\0x89a2c000-dex2jar.jar!\com\google\android\gms\common\api\internal\zacn.class
 * Java compiler version: 6 (50.0)
 * JD-Core Version:       0.7.1
 */