package com.tencent.bugly;

import android.content.Context;
import android.util.Log;
import com.tencent.bugly.proguard.p;
import com.tencent.bugly.proguard.x;
import java.util.ArrayList;
import java.util.List;

public final class b
{
  public static boolean a = true;
  public static List<a> b = new ArrayList();
  public static boolean c;
  private static p d;
  private static boolean e;
  
  public static void a(Context paramContext)
  {
    try
    {
      a(paramContext, null);
      return;
    }
    finally
    {
      paramContext = finally;
      throw paramContext;
    }
  }
  
  public static void a(Context paramContext, BuglyStrategy paramBuglyStrategy)
  {
    try
    {
      if (e)
      {
        x.d("[init] initial Multi-times, ignore this.", new Object[0]);
        return;
      }
      if (paramContext == null)
      {
        Log.w(x.a, "[init] context of init() is null, check it.");
        return;
      }
      com.tencent.bugly.crashreport.common.info.a locala = com.tencent.bugly.crashreport.common.info.a.a(paramContext);
      if (a(locala))
      {
        a = false;
        return;
      }
      String str = locala.f();
      if (str == null)
      {
        Log.e(x.a, "[init] meta data of BUGLY_APPID in AndroidManifest.xml should be set.");
        return;
      }
      a(paramContext, str, locala.u, paramBuglyStrategy);
      return;
    }
    finally {}
  }
  
  /* Error */
  public static void a(Context paramContext, String paramString, boolean paramBoolean, BuglyStrategy paramBuglyStrategy)
  {
    // Byte code:
    //   0: ldc 2
    //   2: monitorenter
    //   3: getstatic 30	com/tencent/bugly/b:e	Z
    //   6: ifeq +17 -> 23
    //   9: ldc 32
    //   11: iconst_0
    //   12: anewarray 4	java/lang/Object
    //   15: invokestatic 37	com/tencent/bugly/proguard/x:d	(Ljava/lang/String;[Ljava/lang/Object;)Z
    //   18: pop
    //   19: ldc 2
    //   21: monitorexit
    //   22: return
    //   23: aload_0
    //   24: ifnonnull +16 -> 40
    //   27: getstatic 40	com/tencent/bugly/proguard/x:a	Ljava/lang/String;
    //   30: ldc 76
    //   32: invokestatic 48	android/util/Log:w	(Ljava/lang/String;Ljava/lang/String;)I
    //   35: pop
    //   36: ldc 2
    //   38: monitorexit
    //   39: return
    //   40: aload_1
    //   41: ifnonnull +16 -> 57
    //   44: getstatic 40	com/tencent/bugly/proguard/x:a	Ljava/lang/String;
    //   47: ldc 78
    //   49: invokestatic 66	android/util/Log:e	(Ljava/lang/String;Ljava/lang/String;)I
    //   52: pop
    //   53: ldc 2
    //   55: monitorexit
    //   56: return
    //   57: iconst_1
    //   58: putstatic 30	com/tencent/bugly/b:e	Z
    //   61: iload_2
    //   62: ifeq +91 -> 153
    //   65: iconst_1
    //   66: putstatic 80	com/tencent/bugly/b:c	Z
    //   69: iconst_1
    //   70: putstatic 82	com/tencent/bugly/proguard/x:b	Z
    //   73: ldc 84
    //   75: iconst_0
    //   76: anewarray 4	java/lang/Object
    //   79: invokestatic 37	com/tencent/bugly/proguard/x:d	(Ljava/lang/String;[Ljava/lang/Object;)Z
    //   82: pop
    //   83: ldc 86
    //   85: iconst_0
    //   86: anewarray 4	java/lang/Object
    //   89: invokestatic 88	com/tencent/bugly/proguard/x:e	(Ljava/lang/String;[Ljava/lang/Object;)Z
    //   92: pop
    //   93: ldc 90
    //   95: iconst_0
    //   96: anewarray 4	java/lang/Object
    //   99: invokestatic 37	com/tencent/bugly/proguard/x:d	(Ljava/lang/String;[Ljava/lang/Object;)Z
    //   102: pop
    //   103: ldc 92
    //   105: iconst_0
    //   106: anewarray 4	java/lang/Object
    //   109: invokestatic 37	com/tencent/bugly/proguard/x:d	(Ljava/lang/String;[Ljava/lang/Object;)Z
    //   112: pop
    //   113: ldc 94
    //   115: iconst_0
    //   116: anewarray 4	java/lang/Object
    //   119: invokestatic 37	com/tencent/bugly/proguard/x:d	(Ljava/lang/String;[Ljava/lang/Object;)Z
    //   122: pop
    //   123: ldc 96
    //   125: iconst_0
    //   126: anewarray 4	java/lang/Object
    //   129: invokestatic 37	com/tencent/bugly/proguard/x:d	(Ljava/lang/String;[Ljava/lang/Object;)Z
    //   132: pop
    //   133: ldc 86
    //   135: iconst_0
    //   136: anewarray 4	java/lang/Object
    //   139: invokestatic 88	com/tencent/bugly/proguard/x:e	(Ljava/lang/String;[Ljava/lang/Object;)Z
    //   142: pop
    //   143: ldc 98
    //   145: iconst_0
    //   146: anewarray 4	java/lang/Object
    //   149: invokestatic 100	com/tencent/bugly/proguard/x:b	(Ljava/lang/String;[Ljava/lang/Object;)Z
    //   152: pop
    //   153: ldc 102
    //   155: iconst_0
    //   156: anewarray 4	java/lang/Object
    //   159: invokestatic 104	com/tencent/bugly/proguard/x:a	(Ljava/lang/String;[Ljava/lang/Object;)Z
    //   162: pop
    //   163: ldc 106
    //   165: iconst_0
    //   166: anewarray 4	java/lang/Object
    //   169: invokestatic 100	com/tencent/bugly/proguard/x:b	(Ljava/lang/String;[Ljava/lang/Object;)Z
    //   172: pop
    //   173: ldc 108
    //   175: iconst_1
    //   176: anewarray 4	java/lang/Object
    //   179: dup
    //   180: iconst_0
    //   181: ldc 110
    //   183: aastore
    //   184: invokestatic 104	com/tencent/bugly/proguard/x:a	(Ljava/lang/String;[Ljava/lang/Object;)Z
    //   187: pop
    //   188: aload_0
    //   189: invokestatic 115	com/tencent/bugly/proguard/z:a	(Landroid/content/Context;)Landroid/content/Context;
    //   192: astore 8
    //   194: aload 8
    //   196: invokestatic 53	com/tencent/bugly/crashreport/common/info/a:a	(Landroid/content/Context;)Lcom/tencent/bugly/crashreport/common/info/a;
    //   199: astore 11
    //   201: aload 11
    //   203: invokevirtual 118	com/tencent/bugly/crashreport/common/info/a:p	()Ljava/lang/String;
    //   206: pop
    //   207: aload 8
    //   209: invokestatic 122	com/tencent/bugly/proguard/y:a	(Landroid/content/Context;)V
    //   212: aload 8
    //   214: getstatic 23	com/tencent/bugly/b:b	Ljava/util/List;
    //   217: invokestatic 127	com/tencent/bugly/proguard/p:a	(Landroid/content/Context;Ljava/util/List;)Lcom/tencent/bugly/proguard/p;
    //   220: putstatic 129	com/tencent/bugly/b:d	Lcom/tencent/bugly/proguard/p;
    //   223: aload 8
    //   225: invokestatic 134	com/tencent/bugly/proguard/u:a	(Landroid/content/Context;)Lcom/tencent/bugly/proguard/u;
    //   228: pop
    //   229: aload 8
    //   231: getstatic 23	com/tencent/bugly/b:b	Ljava/util/List;
    //   234: invokestatic 139	com/tencent/bugly/crashreport/common/strategy/a:a	(Landroid/content/Context;Ljava/util/List;)Lcom/tencent/bugly/crashreport/common/strategy/a;
    //   237: astore 9
    //   239: aload 8
    //   241: invokestatic 144	com/tencent/bugly/proguard/n:a	(Landroid/content/Context;)Lcom/tencent/bugly/proguard/n;
    //   244: astore 10
    //   246: aload 11
    //   248: invokestatic 56	com/tencent/bugly/b:a	(Lcom/tencent/bugly/crashreport/common/info/a;)Z
    //   251: ifeq +11 -> 262
    //   254: iconst_0
    //   255: putstatic 58	com/tencent/bugly/b:a	Z
    //   258: ldc 2
    //   260: monitorexit
    //   261: return
    //   262: aload 11
    //   264: aload_1
    //   265: invokevirtual 147	com/tencent/bugly/crashreport/common/info/a:a	(Ljava/lang/String;)V
    //   268: ldc -107
    //   270: iconst_1
    //   271: anewarray 4	java/lang/Object
    //   274: dup
    //   275: iconst_0
    //   276: aload_1
    //   277: aastore
    //   278: invokestatic 104	com/tencent/bugly/proguard/x:a	(Ljava/lang/String;[Ljava/lang/Object;)Z
    //   281: pop
    //   282: aload_3
    //   283: ifnull +579 -> 862
    //   286: aload_3
    //   287: invokevirtual 154	com/tencent/bugly/BuglyStrategy:getAppVersion	()Ljava/lang/String;
    //   290: astore_1
    //   291: aload_1
    //   292: invokestatic 160	android/text/TextUtils:isEmpty	(Ljava/lang/CharSequence;)Z
    //   295: ifne +71 -> 366
    //   298: aload_1
    //   299: astore_0
    //   300: aload_1
    //   301: invokevirtual 166	java/lang/String:length	()I
    //   304: bipush 100
    //   306: if_icmple +37 -> 343
    //   309: aload_1
    //   310: iconst_0
    //   311: bipush 100
    //   313: invokevirtual 170	java/lang/String:substring	(II)Ljava/lang/String;
    //   316: astore_0
    //   317: ldc -84
    //   319: iconst_3
    //   320: anewarray 4	java/lang/Object
    //   323: dup
    //   324: iconst_0
    //   325: aload_1
    //   326: aastore
    //   327: dup
    //   328: iconst_1
    //   329: bipush 100
    //   331: invokestatic 178	java/lang/Integer:valueOf	(I)Ljava/lang/Integer;
    //   334: aastore
    //   335: dup
    //   336: iconst_2
    //   337: aload_0
    //   338: aastore
    //   339: invokestatic 37	com/tencent/bugly/proguard/x:d	(Ljava/lang/String;[Ljava/lang/Object;)Z
    //   342: pop
    //   343: aload 11
    //   345: aload_0
    //   346: putfield 181	com/tencent/bugly/crashreport/common/info/a:j	Ljava/lang/String;
    //   349: ldc -73
    //   351: iconst_1
    //   352: anewarray 4	java/lang/Object
    //   355: dup
    //   356: iconst_0
    //   357: aload_3
    //   358: invokevirtual 154	com/tencent/bugly/BuglyStrategy:getAppVersion	()Ljava/lang/String;
    //   361: aastore
    //   362: invokestatic 104	com/tencent/bugly/proguard/x:a	(Ljava/lang/String;[Ljava/lang/Object;)Z
    //   365: pop
    //   366: aload_3
    //   367: invokevirtual 187	com/tencent/bugly/BuglyStrategy:isReplaceOldChannel	()Z
    //   370: ifeq +87 -> 457
    //   373: aload_3
    //   374: invokevirtual 190	com/tencent/bugly/BuglyStrategy:getAppChannel	()Ljava/lang/String;
    //   377: astore_1
    //   378: aload_1
    //   379: invokestatic 160	android/text/TextUtils:isEmpty	(Ljava/lang/CharSequence;)Z
    //   382: ifne +120 -> 502
    //   385: aload_1
    //   386: astore_0
    //   387: aload_1
    //   388: invokevirtual 166	java/lang/String:length	()I
    //   391: bipush 100
    //   393: if_icmple +37 -> 430
    //   396: aload_1
    //   397: iconst_0
    //   398: bipush 100
    //   400: invokevirtual 170	java/lang/String:substring	(II)Ljava/lang/String;
    //   403: astore_0
    //   404: ldc -64
    //   406: iconst_3
    //   407: anewarray 4	java/lang/Object
    //   410: dup
    //   411: iconst_0
    //   412: aload_1
    //   413: aastore
    //   414: dup
    //   415: iconst_1
    //   416: bipush 100
    //   418: invokestatic 178	java/lang/Integer:valueOf	(I)Ljava/lang/Integer;
    //   421: aastore
    //   422: dup
    //   423: iconst_2
    //   424: aload_0
    //   425: aastore
    //   426: invokestatic 37	com/tencent/bugly/proguard/x:d	(Ljava/lang/String;[Ljava/lang/Object;)Z
    //   429: pop
    //   430: getstatic 129	com/tencent/bugly/b:d	Lcom/tencent/bugly/proguard/p;
    //   433: sipush 556
    //   436: ldc -62
    //   438: aload_0
    //   439: invokevirtual 198	java/lang/String:getBytes	()[B
    //   442: aconst_null
    //   443: iconst_0
    //   444: invokevirtual 201	com/tencent/bugly/proguard/p:a	(ILjava/lang/String;[BLcom/tencent/bugly/proguard/o;Z)Z
    //   447: pop
    //   448: aload 11
    //   450: aload_0
    //   451: putfield 204	com/tencent/bugly/crashreport/common/info/a:l	Ljava/lang/String;
    //   454: goto +48 -> 502
    //   457: getstatic 129	com/tencent/bugly/b:d	Lcom/tencent/bugly/proguard/p;
    //   460: sipush 556
    //   463: aconst_null
    //   464: iconst_1
    //   465: invokevirtual 207	com/tencent/bugly/proguard/p:a	(ILcom/tencent/bugly/proguard/o;Z)Ljava/util/Map;
    //   468: astore_0
    //   469: aload_0
    //   470: ifnull +32 -> 502
    //   473: aload_0
    //   474: ldc -62
    //   476: invokeinterface 213 2 0
    //   481: checkcast 215	[B
    //   484: astore_0
    //   485: aload_0
    //   486: ifnull +16 -> 502
    //   489: aload 11
    //   491: new 162	java/lang/String
    //   494: dup
    //   495: aload_0
    //   496: invokespecial 218	java/lang/String:<init>	([B)V
    //   499: putfield 204	com/tencent/bugly/crashreport/common/info/a:l	Ljava/lang/String;
    //   502: ldc -36
    //   504: iconst_1
    //   505: anewarray 4	java/lang/Object
    //   508: dup
    //   509: iconst_0
    //   510: aload 11
    //   512: getfield 204	com/tencent/bugly/crashreport/common/info/a:l	Ljava/lang/String;
    //   515: aastore
    //   516: invokestatic 104	com/tencent/bugly/proguard/x:a	(Ljava/lang/String;[Ljava/lang/Object;)Z
    //   519: pop
    //   520: goto +14 -> 534
    //   523: astore_0
    //   524: getstatic 80	com/tencent/bugly/b:c	Z
    //   527: ifeq +7 -> 534
    //   530: aload_0
    //   531: invokevirtual 223	java/lang/Exception:printStackTrace	()V
    //   534: aload_3
    //   535: invokevirtual 226	com/tencent/bugly/BuglyStrategy:getAppPackageName	()Ljava/lang/String;
    //   538: astore_1
    //   539: aload_1
    //   540: invokestatic 160	android/text/TextUtils:isEmpty	(Ljava/lang/CharSequence;)Z
    //   543: ifne +71 -> 614
    //   546: aload_1
    //   547: astore_0
    //   548: aload_1
    //   549: invokevirtual 166	java/lang/String:length	()I
    //   552: bipush 100
    //   554: if_icmple +37 -> 591
    //   557: aload_1
    //   558: iconst_0
    //   559: bipush 100
    //   561: invokevirtual 170	java/lang/String:substring	(II)Ljava/lang/String;
    //   564: astore_0
    //   565: ldc -28
    //   567: iconst_3
    //   568: anewarray 4	java/lang/Object
    //   571: dup
    //   572: iconst_0
    //   573: aload_1
    //   574: aastore
    //   575: dup
    //   576: iconst_1
    //   577: bipush 100
    //   579: invokestatic 178	java/lang/Integer:valueOf	(I)Ljava/lang/Integer;
    //   582: aastore
    //   583: dup
    //   584: iconst_2
    //   585: aload_0
    //   586: aastore
    //   587: invokestatic 37	com/tencent/bugly/proguard/x:d	(Ljava/lang/String;[Ljava/lang/Object;)Z
    //   590: pop
    //   591: aload 11
    //   593: aload_0
    //   594: putfield 230	com/tencent/bugly/crashreport/common/info/a:c	Ljava/lang/String;
    //   597: ldc -24
    //   599: iconst_1
    //   600: anewarray 4	java/lang/Object
    //   603: dup
    //   604: iconst_0
    //   605: aload_3
    //   606: invokevirtual 226	com/tencent/bugly/BuglyStrategy:getAppPackageName	()Ljava/lang/String;
    //   609: aastore
    //   610: invokestatic 104	com/tencent/bugly/proguard/x:a	(Ljava/lang/String;[Ljava/lang/Object;)Z
    //   613: pop
    //   614: aload_3
    //   615: invokevirtual 235	com/tencent/bugly/BuglyStrategy:getDeviceID	()Ljava/lang/String;
    //   618: astore_1
    //   619: aload_1
    //   620: ifnull +68 -> 688
    //   623: aload_1
    //   624: astore_0
    //   625: aload_1
    //   626: invokevirtual 166	java/lang/String:length	()I
    //   629: bipush 100
    //   631: if_icmple +37 -> 668
    //   634: aload_1
    //   635: iconst_0
    //   636: bipush 100
    //   638: invokevirtual 170	java/lang/String:substring	(II)Ljava/lang/String;
    //   641: astore_0
    //   642: ldc -19
    //   644: iconst_3
    //   645: anewarray 4	java/lang/Object
    //   648: dup
    //   649: iconst_0
    //   650: aload_1
    //   651: aastore
    //   652: dup
    //   653: iconst_1
    //   654: bipush 100
    //   656: invokestatic 178	java/lang/Integer:valueOf	(I)Ljava/lang/Integer;
    //   659: aastore
    //   660: dup
    //   661: iconst_2
    //   662: aload_0
    //   663: aastore
    //   664: invokestatic 37	com/tencent/bugly/proguard/x:d	(Ljava/lang/String;[Ljava/lang/Object;)Z
    //   667: pop
    //   668: aload 11
    //   670: aload_0
    //   671: invokevirtual 239	com/tencent/bugly/crashreport/common/info/a:c	(Ljava/lang/String;)V
    //   674: ldc -15
    //   676: iconst_1
    //   677: anewarray 4	java/lang/Object
    //   680: dup
    //   681: iconst_0
    //   682: aload_0
    //   683: aastore
    //   684: invokestatic 104	com/tencent/bugly/proguard/x:a	(Ljava/lang/String;[Ljava/lang/Object;)Z
    //   687: pop
    //   688: aload_3
    //   689: invokevirtual 244	com/tencent/bugly/BuglyStrategy:getDeviceModel	()Ljava/lang/String;
    //   692: astore_0
    //   693: aload_0
    //   694: ifnull +23 -> 717
    //   697: aload 11
    //   699: aload_0
    //   700: invokevirtual 246	com/tencent/bugly/crashreport/common/info/a:d	(Ljava/lang/String;)V
    //   703: ldc -8
    //   705: iconst_1
    //   706: anewarray 4	java/lang/Object
    //   709: dup
    //   710: iconst_0
    //   711: aload_0
    //   712: aastore
    //   713: invokestatic 104	com/tencent/bugly/proguard/x:a	(Ljava/lang/String;[Ljava/lang/Object;)Z
    //   716: pop
    //   717: aload 11
    //   719: aload_3
    //   720: invokevirtual 251	com/tencent/bugly/BuglyStrategy:isUploadProcess	()Z
    //   723: putfield 252	com/tencent/bugly/crashreport/common/info/a:e	Z
    //   726: aload_3
    //   727: invokevirtual 255	com/tencent/bugly/BuglyStrategy:isBuglyLogUpload	()Z
    //   730: putstatic 256	com/tencent/bugly/proguard/y:a	Z
    //   733: goto +129 -> 862
    //   736: getstatic 23	com/tencent/bugly/b:b	Ljava/util/List;
    //   739: invokeinterface 261 1 0
    //   744: istore 5
    //   746: iload 4
    //   748: iload 5
    //   750: if_icmpge +65 -> 815
    //   753: aload 10
    //   755: getstatic 23	com/tencent/bugly/b:b	Ljava/util/List;
    //   758: iload 4
    //   760: invokeinterface 264 2 0
    //   765: checkcast 266	com/tencent/bugly/a
    //   768: getfield 270	com/tencent/bugly/a:id	I
    //   771: invokevirtual 273	com/tencent/bugly/proguard/n:a	(I)Z
    //   774: ifeq +94 -> 868
    //   777: getstatic 23	com/tencent/bugly/b:b	Ljava/util/List;
    //   780: iload 4
    //   782: invokeinterface 264 2 0
    //   787: checkcast 266	com/tencent/bugly/a
    //   790: aload 8
    //   792: iload_2
    //   793: aload_3
    //   794: invokevirtual 277	com/tencent/bugly/a:init	(Landroid/content/Context;ZLcom/tencent/bugly/BuglyStrategy;)V
    //   797: goto +71 -> 868
    //   800: astore_0
    //   801: aload_0
    //   802: invokestatic 280	com/tencent/bugly/proguard/x:a	(Ljava/lang/Throwable;)Z
    //   805: ifne +63 -> 868
    //   808: aload_0
    //   809: invokevirtual 283	java/lang/Throwable:printStackTrace	()V
    //   812: goto +56 -> 868
    //   815: aload 8
    //   817: aload_3
    //   818: invokestatic 286	com/tencent/bugly/crashreport/biz/b:a	(Landroid/content/Context;Lcom/tencent/bugly/BuglyStrategy;)V
    //   821: aload_3
    //   822: ifnull +55 -> 877
    //   825: aload_3
    //   826: invokevirtual 290	com/tencent/bugly/BuglyStrategy:getAppReportDelay	()J
    //   829: lstore 6
    //   831: goto +3 -> 834
    //   834: aload 9
    //   836: lload 6
    //   838: invokevirtual 293	com/tencent/bugly/crashreport/common/strategy/a:a	(J)V
    //   841: ldc_w 295
    //   844: iconst_0
    //   845: anewarray 4	java/lang/Object
    //   848: invokestatic 100	com/tencent/bugly/proguard/x:b	(Ljava/lang/String;[Ljava/lang/Object;)Z
    //   851: pop
    //   852: ldc 2
    //   854: monitorexit
    //   855: return
    //   856: astore_0
    //   857: ldc 2
    //   859: monitorexit
    //   860: aload_0
    //   861: athrow
    //   862: iconst_0
    //   863: istore 4
    //   865: goto -129 -> 736
    //   868: iload 4
    //   870: iconst_1
    //   871: iadd
    //   872: istore 4
    //   874: goto -138 -> 736
    //   877: lconst_0
    //   878: lstore 6
    //   880: goto -46 -> 834
    // Local variable table:
    //   start	length	slot	name	signature
    //   0	883	0	paramContext	Context
    //   0	883	1	paramString	String
    //   0	883	2	paramBoolean	boolean
    //   0	883	3	paramBuglyStrategy	BuglyStrategy
    //   746	127	4	i	int
    //   744	7	5	j	int
    //   829	50	6	l	long
    //   192	624	8	localContext	Context
    //   237	598	9	locala	com.tencent.bugly.crashreport.common.strategy.a
    //   244	510	10	localn	com.tencent.bugly.proguard.n
    //   199	519	11	locala1	com.tencent.bugly.crashreport.common.info.a
    // Exception table:
    //   from	to	target	type
    //   366	385	523	java/lang/Exception
    //   387	430	523	java/lang/Exception
    //   430	454	523	java/lang/Exception
    //   457	469	523	java/lang/Exception
    //   473	485	523	java/lang/Exception
    //   489	502	523	java/lang/Exception
    //   502	520	523	java/lang/Exception
    //   753	797	800	finally
    //   3	19	856	finally
    //   27	36	856	finally
    //   44	53	856	finally
    //   57	61	856	finally
    //   65	153	856	finally
    //   153	258	856	finally
    //   262	282	856	finally
    //   286	298	856	finally
    //   300	343	856	finally
    //   343	366	856	finally
    //   366	385	856	finally
    //   387	430	856	finally
    //   430	454	856	finally
    //   457	469	856	finally
    //   473	485	856	finally
    //   489	502	856	finally
    //   502	520	856	finally
    //   524	534	856	finally
    //   534	546	856	finally
    //   548	591	856	finally
    //   591	614	856	finally
    //   614	619	856	finally
    //   625	668	856	finally
    //   668	688	856	finally
    //   688	693	856	finally
    //   697	717	856	finally
    //   717	733	856	finally
    //   736	746	856	finally
    //   801	812	856	finally
    //   815	821	856	finally
    //   825	831	856	finally
    //   834	852	856	finally
  }
  
  public static void a(a parama)
  {
    try
    {
      if (!b.contains(parama)) {
        b.add(parama);
      }
      return;
    }
    finally
    {
      parama = finally;
      throw parama;
    }
  }
  
  private static boolean a(com.tencent.bugly.crashreport.common.info.a parama)
  {
    List localList = parama.o;
    parama.getClass();
    return (localList != null) && (localList.contains("bugly"));
  }
}


/* Location:              C:\Users\adinb\Downloads\dex2jar-2.0\dex2jar-2.0\0x89a2c000-dex2jar.jar!\com\tencent\bugly\b.class
 * Java compiler version: 6 (50.0)
 * JD-Core Version:       0.7.1
 */